Workbook

Sheet Summary
A1: Gratuity DBO: Summary of Results
A2: ILLUSTRATIVE MODEL USING SYNTHETIC DATA. Assumptions are placeholders; see the Assumptions sheet.
A4: Measure | B4: Value
A5: Number of employees | B5: =COUNTA(Census!$A$6:$A$155) -> 150
A6: Employees eligible today (service >= 5 years) | B6: =SUM(Census!$K$6:$K$155) -> 100
A7: Defined Benefit Obligation, DBO (Rs) | B7: =SUM(Census!$L$6:$L$155) -> 46785528
A8: Current service cost, next year (Rs) | B8: =SUM(Census!$M$6:$M$155) -> 3723248.4
A9: Interest cost, next year, approx. = discount rate x DBO (Rs) | B9: =Assumptions!$B$8*B7 -> 3274986.9
A10: Expected payments in year 1 for service earned to date (Rs) | B10: =B20 -> 3990406
A11: Weighted average term of the liability (years) | B11: =SUMPRODUCT(A20:A64,D20:D64)/SUM(D20:D64) -> 8.675623
A12: Benefit if all eligible employees left today (Rs) | B12: =SUMPRODUCT(Census!$J$6:$J$155,Census!$K$6:$K$155) -> 78425827
A13: DBO as % of that reference figure | B13: =B7/B12 -> 0.59655766
A14: Share of DBO held by the top 10 employees | B14: =SUMPRODUCT(LARGE(Census!$L$6:$L$155,{1,2,3,4,5,6,7,8,9,10}))/B7 -> 0.22813265
A16: Reconciliation: PV of cash flows below minus DBO (should be 0) | B16: =SUM(D20:D64)-B7 -> 0
A18: Expected payments for service earned to date, by future year
A19: Year from valuation date (t) | B19: Expected payments, undiscounted (Rs) | C19: Discount factor | D19: Present value (Rs)
A20: 1 | B20: =SUMPRODUCT(INDEX(Benefit_Grid!$C$6:$AU$155,0,A20)*Census!$F$6:$F$155/(Census!$F$6:$F$155+A20)) -> 3990406 | C20: =(1/(1+Assumptions!$B$8))^A20 -> 0.93457944 | D20: =B20*C20 -> 3729351.4
A21: =A20+1 -> 2 | B21: =SUMPRODUCT(INDEX(Benefit_Grid!$C$6:$AU$155,0,A21)*Census!$F$6:$F$155/(Census!$F$6:$F$155+A21)) -> 3726064.7 | C21: =(1/(1+Assumptions!$B$8))^A21 -> 0.87343873 | D21: =B21*C21 -> 3254489.2
A22: =A21+1 -> 3 | B22: =SUMPRODUCT(INDEX(Benefit_Grid!$C$6:$AU$155,0,A22)*Census!$F$6:$F$155/(Census!$F$6:$F$155+A22)) -> 3403823.1 | C22: =(1/(1+Assumptions!$B$8))^A22 -> 0.81629788 | D22: =B22*C22 -> 2778533.5
A23: =A22+1 -> 4 | B23: =SUMPRODUCT(INDEX(Benefit_Grid!$C$6:$AU$155,0,A23)*Census!$F$6:$F$155/(Census!$F$6:$F$155+A23)) -> 3094926.5 | C23: =(1/(1+Assumptions!$B$8))^A23 -> 0.76289521 | D23: =B23*C23 -> 2361104.6
A24: =A23+1 -> 5 | B24: =SUMPRODUCT(INDEX(Benefit_Grid!$C$6:$AU$155,0,A24)*Census!$F$6:$F$155/(Census!$F$6:$F$155+A24)) -> 7603910.9 | C24: =(1/(1+Assumptions!$B$8))^A24 -> 0.71298618 | D24: =B24*C24 -> 5421483.4
A25: =A24+1 -> 6 | B25: =SUMPRODUCT(INDEX(Benefit_Grid!$C$6:$AU$155,0,A25)*Census!$F$6:$F$155/(Census!$F$6:$F$155+A25)) -> 3998581.8 | C25: =(1/(1+Assumptions!$B$8))^A25 -> 0.66634222 | D25: =B25*C25 -> 2664423.9
A26: =A25+1 -> 7 | B26: =SUMPRODUCT(INDEX(Benefit_Grid!$C$6:$AU$155,0,A26)*Census!$F$6:$F$155/(Census!$F$6:$F$155+A26)) -> 6388681.3 | C26: =(1/(1+Assumptions!$B$8))^A26 -> 0.62274974 | D26: =B26*C26 -> 3978549.6
A27: =A26+1 -> 8 | B27: =SUMPRODUCT(INDEX(Benefit_Grid!$C$6:$AU$155,0,A27)*Census!$F$6:$F$155/(Census!$F$6:$F$155+A27)) -> 4737826.8 | C27: =(1/(1+Assumptions!$B$8))^A27 -> 0.5820091 | D27: =B27*C27 -> 2757458.3
A28: =A27+1 -> 9 | B28: =SUMPRODUCT(INDEX(Benefit_Grid!$C$6:$AU$155,0,A28)*Census!$F$6:$F$155/(Census!$F$6:$F$155+A28)) -> 2915160.1 | C28: =(1/(1+Assumptions!$B$8))^A28 -> 0.54393374 | D28: =B28*C28 -> 1585654
A29: =A28+1 -> 10 | B29: =SUMPRODUCT(INDEX(Benefit_Grid!$C$6:$AU$155,0,A29)*Census!$F$6:$F$155/(Census!$F$6:$F$155+A29)) -> 4904407.7 | C29: =(1/(1+Assumptions!$B$8))^A29 -> 0.50834929 | D29: =B29*C29 -> 2493152.2
A30: =A29+1 -> 11 | B30: =SUMPRODUCT(INDEX(Benefit_Grid!$C$6:$AU$155,0,A30)*Census!$F$6:$F$155/(Census!$F$6:$F$155+A30)) -> 6515531.9 | C30: =(1/(1+Assumptions!$B$8))^A30 -> 0.4750928 | D30: =B30*C30 -> 3095482.3
A31: =A30+1 -> 12 | B31: =SUMPRODUCT(INDEX(Benefit_Grid!$C$6:$AU$155,0,A31)*Census!$F$6:$F$155/(Census!$F$6:$F$155+A31)) -> 4847983.4 | C31: =(1/(1+Assumptions!$B$8))^A31 -> 0.44401196 | D31: =B31*C31 -> 2152562.6
A32: =A31+1 -> 13 | B32: =SUMPRODUCT(INDEX(Benefit_Grid!$C$6:$AU$155,0,A32)*Census!$F$6:$F$155/(Census!$F$6:$F$155+A32)) -> 4521481.3 | C32: =(1/(1+Assumptions!$B$8))^A32 -> 0.41496445 | D32: =B32*C32 -> 1876254
... A64: =A63+1 -> 45 | B64: =SUMPRODUCT(INDEX(Benefit_Grid!$C$6:$AU$155,0,A64)*Census!$F$6:$F$155/(Census!$F$6:$F$155+A64)) -> 0 | C64: =(1/(1+Assumptions!$B$8))^A64 -> 0.047613489 | D64: =B64*C64 -> 0

Sheet Assumptions
A1: Gratuity Valuation (Projected Unit Credit): Assumptions
A2: ILLUSTRATIVE MODEL USING SYNTHETIC DATA. Not a real valuation.
A3: Legend: blue text = input you may edit; black = formula; yellow fill = key assumption.
A5: Assumption | B5: Value | C5: Basis / note
A6: Valuation date | B6: 46112 | C6: A financial year-end (chosen by the project).
A7: Retirement age (years) | B7: 60 | C7: Common assumption; the Stage 1 data check also uses 60.
A8: Discount rate | B8: 0.07 | C8: Proxy: 10-year government bond yield near 31 March 2026 (about 7.00% per a Trading Economics table; approximate, cite your source).
A9: Salary escalation (per year) | B9: 0.08 | C9: Illustrative judgement; in a real valuation it follows the employer's pay policy.
A10: Ceiling on gratuity (Rs) | B10: 2000000 | C10: Rs 20 lakh. Verify against the current notification.
A11: Minimum service for withdrawal benefit (years) | B11: 5 | C11: Five-year rule for exits other than death (and retirement here).
A12: Mortality A (Gompertz-Makeham) | B12: 0.0004 | C12: ILLUSTRATIVE placeholder; replace with the published IALM table.
A13: Mortality B | B13: 2e-05 | C13: ILLUSTRATIVE placeholder.
A14: Mortality c | B14: 1.1 | C14: ILLUSTRATIVE placeholder.
A17: Illustrative annual withdrawal rates by age band
A18: From age | B18: To age (exclusive) | C18: Annual withdrawal rate
A19: 18 | B19: 25 | C19: 0.2
A20: 25 | B20: 30 | C20: 0.15
A21: 30 | B21: 35 | C21: 0.11
A22: 35 | B22: 40 | C22: 0.08
A23: 40 | B23: 45 | C23: 0.05
A24: 45 | B24: 50 | C24: 0.03
A25: 50 | B25: 55 | C25: 0.02
A26: 55 | B26: 60 | C26: 0.01
A27: 60 | B27: 200 | C27: 0
A29: Rates are illustrative placeholders, not company or industry data.

Sheet Census
A1: Employee census and per-employee valuation
A2: SYNTHETIC DATA generated for learning (seed 2026). Columns A-D are inputs; E-M are formulas; N is the Python result pasted for cross-checking.
A3: DBO = sum over exit years of [expected benefit x service now / service at exit x discount factor]. See Benefit_Grid for the expected benefit by year.
A5: Emp ID | B5: Date of birth | C5: Date of joining | D5: Monthly wages (Rs) | E5: Age at valuation | F5: Service at valuation (years) | G5: Start age (rounded down) | H5: Years to retirement | I5: Years for formula (part-year rule) | J5: Benefit if exit today (Rs) | K5: Eligible today (1 = yes) | L5: DBO (Rs) | M5: Current service cost (Rs) | N5: Python DBO (Rs) | O5: Excel minus Python (Rs)
A6: E001 | B6: 35146 | C6: 44914 | D6: 23700 | E6: =(Assumptions!$B$6-B6)/365.25 -> 30.023272 | F6: =(Assumptions!$B$6-C6)/365.25 -> 3.2799452 | G6: =INT(E6) -> 30 | H6: =Assumptions!$B$7-G6 -> 30 | I6: =INT(F6)+IF(F6-INT(F6)>0.5,1,0) -> 3 | J6: =MIN(15/26*D6*I6,Assumptions!$B$10) -> 41019.231 | K6: =IF(F6>=Assumptions!$B$11,1,0) -> 0 | L6: =SUMPRODUCT(Benefit_Grid!$C6:$AU6*(F6/(F6+Benefit_Grid!$C$5:$AU$5))*(1/(1+Assumptions!$B$8))^Benefit_Grid!$C$5:$AU$5) -> 37093.242 | M6: =SUMPRODUCT(Benefit_Grid!$C6:$AU6/(F6+Benefit_Grid!$C$5:$AU$5)*(1/(1+Assumptions!$B$8))^Benefit_Grid!$C$5:$AU$5) -> 11309.104 | N6: 37093.242 | O6: =L6-N6 -> 3.4830009e-07
A7: E002 | B7: 33903 | C7: 45147 | D7: 33500 | E7: =(Assumptions!$B$6-B7)/365.25 -> 33.42642 | F7: =(Assumptions!$B$6-C7)/365.25 -> 2.642026 | G7: =INT(E7) -> 33 | H7: =Assumptions!$B$7-G7 -> 27 | I7: =INT(F7)+IF(F7-INT(F7)>0.5,1,0) -> 3 | J7: =MIN(15/26*D7*I7,Assumptions!$B$10) -> 57980.769 | K7: =IF(F7>=Assumptions!$B$11,1,0) -> 0 | L7: =SUMPRODUCT(Benefit_Grid!$C7:$AU7*(F7/(F7+Benefit_Grid!$C$5:$AU$5))*(1/(1+Assumptions!$B$8))^Benefit_Grid!$C$5:$AU$5) -> 36812.585 | M7: =SUMPRODUCT(Benefit_Grid!$C7:$AU7/(F7+Benefit_Grid!$C$5:$AU$5)*(1/(1+Assumptions!$B$8))^Benefit_Grid!$C$5:$AU$5) -> 13933.468 | N7: 36812.585 | O7: =L7-N7 -> 3.4522236e-07
A8: E003 | B8: 31513 | C8: 41035 | D8: 99400 | E8: =(Assumptions!$B$6-B8)/365.25 -> 39.969884 | F8: =(Assumptions!$B$6-C8)/365.25 -> 13.900068 | G8: =INT(E8) -> 39 | H8: =Assumptions!$B$7-G8 -> 21 | I8: =INT(F8)+IF(F8-INT(F8)>0.5,1,0) -> 14 | J8: =MIN(15/26*D8*I8,Assumptions!$B$10) -> 802846.15 | K8: =IF(F8>=Assumptions!$B$11,1,0) -> 1 | L8: =SUMPRODUCT(Benefit_Grid!$C8:$AU8*(F8/(F8+Benefit_Grid!$C$5:$AU$5))*(1/(1+Assumptions!$B$8))^Benefit_Grid!$C$5:$AU$5) -> 445115.16 | M8: =SUMPRODUCT(Benefit_Grid!$C8:$AU8/(F8+Benefit_Grid!$C$5:$AU$5)*(1/(1+Assumptions!$B$8))^Benefit_Grid!$C$5:$AU$5) -> 32022.516 | N8: 445115.16 | O8: =L8-N8 -> 1.1554221e-07
A9: E004 | B9: 31671 | C9: 44015 | D9: 44200 | E9: =(Assumptions!$B$6-B9)/365.25 -> 39.537303 | F9: =(Assumptions!$B$6-C9)/365.25 -> 5.7412731 | G9: =INT(E9) -> 39 | H9: =Assumptions!$B$7-G9 -> 21 | I9: =INT(F9)+IF(F9-INT(F9)>0.5,1,0) -> 6 | J9: =MIN(15/26*D9*I9,Assumptions!$B$10) -> 153000 | K9: =IF(F9>=Assumptions!$B$11,1,0) -> 1 | L9: =SUMPRODUCT(Benefit_Grid!$C9:$AU9*(F9/(F9+Benefit_Grid!$C$5:$AU$5))*(1/(1+Assumptions!$B$8))^Benefit_Grid!$C$5:$AU$5) -> 130464.78 | M9: =SUMPRODUCT(Benefit_Grid!$C9:$AU9/(F9+Benefit_Grid!$C$5:$AU$5)*(1/(1+Assumptions!$B$8))^Benefit_Grid!$C$5:$AU$5) -> 22724.016 | N9: 130464.78 | O9: =L9-N9 -> 2.6584894e-07
A10: E005 | B10: 33227 | C10: 42657 | D10: 49000 | E10: =(Assumptions!$B$6-B10)/365.25 -> 35.277207 | F10: =(Assumptions!$B$6-C10)/365.25 -> 9.4592745 | G10: =INT(E10) -> 35 | H10: =Assumptions!$B$7-G10 -> 25 | I10: =INT(F10)+IF(F10-INT(F10)>0.5,1,0) -> 9 | J10: =MIN(15/26*D10*I10,Assumptions!$B$10) -> 254423.08 | K10: =IF(F10>=Assumptions!$B$11,1,0) -> 1 | L10: =SUMPRODUCT(Benefit_Grid!$C10:$AU10*(F10/(F10+Benefit_Grid!$C$5:$AU$5))*(1/(1+Assumptions!$B$8))^Benefit_Grid!$C$5:$AU$5) -> 204697.4 | M10: =SUMPRODUCT(Benefit_Grid!$C10:$AU10/(F10+Benefit_Grid!$C$5:$AU$5)*(1/(1+Assumptions!$B$8))^Benefit_Grid!$C$5:$AU$5) -> 21639.863 | N10: 204697.4 | O10: =L10-N10 -> 1.5413389e-07
A11: E006 | B11: 32623 | C11: 42793 | D11: 51100 | E11: =(Assumptions!$B$6-B11)/365.25 -> 36.930869 | F11: =(Assumptions!$B$6-C11)/365.25 -> 9.0869268 | G11: =INT(E11) -> 36 | H11: =Assumptions!$B$7-G11 -> 24 | I11: =INT(F11)+IF(F11-INT(F11)>0.5,1,0) -> 9 | J11: =MIN(15/26*D11*I11,Assumptions!$B$10) -> 265326.92 | K11: =IF(F11>=Assumptions!$B$11,1,0) -> 1 | L11: =SUMPRODUCT(Benefit_Grid!$C11:$AU11*(F11/(F11+Benefit_Grid!$C$5:$AU$5))*(1/(1+Assumptions!$B$8))^Benefit_Grid!$C$5:$AU$5) -> 206758.63 | M11: =SUMPRODUCT(Benefit_Grid!$C11:$AU11/(F11+Benefit_Grid!$C$5:$AU$5)*(1/(1+Assumptions!$B$8))^Benefit_Grid!$C$5:$AU$5) -> 22753.417 | N11: 206758.63 | O11: =L11-N11 -> -4.0023588e-07
A12: E007 | B12: 33233 | C12: 42799 | D12: 49800 | E12: =(Assumptions!$B$6-B12)/365.25 -> 35.26078 | F12: =(Assumptions!$B$6-C12)/365.25 -> 9.0704997 | G12: =INT(E12) -> 35 | H12: =Assumptions!$B$7-G12 -> 25 | I12: =INT(F12)+IF(F12-INT(F12)>0.5,1,0) -> 9 | J12: =MIN(15/26*D12*I12,Assumptions!$B$10) -> 258576.92 | K12: =IF(F12>=Assumptions!$B$11,1,0) -> 1 | L12: =SUMPRODUCT(Benefit_Grid!$C12:$AU12*(F12/(F12+Benefit_Grid!$C$5:$AU$5))*(1/(1+Assumptions!$B$8))^Benefit_Grid!$C$5:$AU$5) -> 203499.05 | M12: =SUMPRODUCT(Benefit_Grid!$C12:$AU12/(F12+Benefit_Grid!$C$5:$AU$5)*(1/(1+Assumptions!$B$8))^Benefit_Grid!$C$5:$AU$5) -> 22435.263 | N12: 203499.05 | O12: =L12-N12 -> -5.387119e-08
A13: E008 | B13: 33325 | C13: 42524 | D13: 45700 | E13: =(Assumptions!$B$6-B13)/365.25 -> 35.008898 | F13: =(Assumptions!$B$6-C13)/365.25 -> 9.8234086 | G13: =INT(E13) -> 35 | H13: =Assumptions!$B$7-G13 -> 25 | I13: =INT(F13)+IF(F13-INT(F13)>0.5,1,0) -> 10 | J13: =MIN(15/26*D13*I13,Assumptions!$B$10) -> 263653.85 | K13: =IF(F13>=Assumptions!$B$11,1,0) -> 1 | L13: =SUMPRODUCT(Benefit_Grid!$C13:$AU13*(F13/(F13+Benefit_Grid!$C$5:$AU$5))*(1/(1+Assumptions!$B$8))^Benefit_Grid!$C$5:$AU$5) -> 208166.93 | M13: =SUMPRODUCT(Benefit_Grid!$C13:$AU13/(F13+Benefit_Grid!$C$5:$AU$5)*(1/(1+Assumptions!$B$8))^Benefit_Grid!$C$5:$AU$5) -> 21190.906 | N13: 208166.93 | O13: =L13-N13 -> 1.9473373e-07
A14: E009 | B14: 33971 | C14: 45857 | D14: 25500 | E14: =(Assumptions!$B$6-B14)/365.25 -> 33.240246 | F14: =(Assumptions!$B$6-C14)/365.25 -> 0.69815195 | G14: =INT(E14) -> 33 | H14: =Assumptions!$B$7-G14 -> 27 | I14: =INT(F14)+IF(F14-INT(F14)>0.5,1,0) -> 1 | J14: =MIN(15/26*D14*I14,Assumptions!$B$10) -> 14711.538 | K14: =IF(F14>=Assumptions!$B$11,1,0) -> 0 | L14: =SUMPRODUCT(Benefit_Grid!$C14:$AU14*(F14/(F14+Benefit_Grid!$C$5:$AU$5))*(1/(1+Assumptions!$B$8))^Benefit_Grid!$C$5:$AU$5) -> 6804.4051 | M14: =SUMPRODUCT(Benefit_Grid!$C14:$AU14/(F14+Benefit_Grid!$C$5:$AU$5)*(1/(1+Assumptions!$B$8))^Benefit_Grid!$C$5:$AU$5) -> 9746.3097 | N14: 6804.4051 | O14: =L14-N14 -> 2.8066734e-07
A15: E010 | B15: 28454 | C15: 38107 | D15: 165000 | E15: =(Assumptions!$B$6-B15)/365.25 -> 48.344969 | F15: =(Assumptions!$B$6-C15)/365.25 -> 21.916496 | G15: =INT(E15) -> 48 | H15: =Assumptions!$B$7-G15 -> 12 | I15: =INT(F15)+IF(F15-INT(F15)>0.5,1,0) -> 22 | J15: =MIN(15/26*D15*I15,Assumptions!$B$10) -> 2000000 | K15: =IF(F15>=Assumptions!$B$11,1,0) -> 1 | L15: =SUMPRODUCT(Benefit_Grid!$C15:$AU15*(F15/(F15+Benefit_Grid!$C$5:$AU$5))*(1/(1+Assumptions!$B$8))^Benefit_Grid!$C$5:$AU$5) -> 716430.24 | M15: =SUMPRODUCT(Benefit_Grid!$C15:$AU15/(F15+Benefit_Grid!$C$5:$AU$5)*(1/(1+Assumptions!$B$8))^Benefit_Grid!$C$5:$AU$5) -> 32689.088 | N15: 716430.24 | O15: =L15-N15 -> -3.7171412e-07
A16: E011 | B16: 34533 | C16: 44930 | D16: 32700 | E16: =(Assumptions!$B$6-B16)/365.25 -> 31.701574 | F16: =(Assumptions!$B$6-C16)/365.25 -> 3.2361396 | G16: =INT(E16) -> 31 | H16: =Assumptions!$B$7-G16 -> 29 | I16: =INT(F16)+IF(F16-INT(F16)>0.5,1,0) -> 3 | J16: =MIN(15/26*D16*I16,Assumptions!$B$10) -> 56596.154 | K16: =IF(F16>=Assumptions!$B$11,1,0) -> 0 | L16: =SUMPRODUCT(Benefit_Grid!$C16:$AU16*(F16/(F16+Benefit_Grid!$C$5:$AU$5))*(1/(1+Assumptions!$B$8))^Benefit_Grid!$C$5:$AU$5) -> 47952.243 | M16: =SUMPRODUCT(Benefit_Grid!$C16:$AU16/(F16+Benefit_Grid!$C$5:$AU$5)*(1/(1+Assumptions!$B$8))^Benefit_Grid!$C$5:$AU$5) -> 14817.73 | N16: 47952.243 | O16: =L16-N16 -> -2.2353197e-07
A17: E012 | B17: 32170 | C17: 41013 | D17: 139100 | E17: =(Assumptions!$B$6-B17)/365.25 -> 38.171116 | F17: =(Assumptions!$B$6-C17)/365.25 -> 13.960301 | G17: =INT(E17) -> 38 | H17: =Assumptions!$B$7-G17 -> 22 | I17: =INT(F17)+IF(F17-INT(F17)>0.5,1,0) -> 14 | J17: =MIN(15/26*D17*I17,Assumptions!$B$10) -> 1123500 | K17: =IF(F17>=Assumptions!$B$11,1,0) -> 1 | L17: =SUMPRODUCT(Benefit_Grid!$C17:$AU17*(F17/(F17+Benefit_Grid!$C$5:$AU$5))*(1/(1+Assumptions!$B$8))^Benefit_Grid!$C$5:$AU$5) -> 548205.22 | M17: =SUMPRODUCT(Benefit_Grid!$C17:$AU17/(F17+Benefit_Grid!$C$5:$AU$5)*(1/(1+Assumptions!$B$8))^Benefit_Grid!$C$5:$AU$5) -> 39268.867 | N17: 548205.22 | O17: =L17-N17 -> 3.8207509e-07
... A155: E150 | B155: 29779 | C155: 40610 | D155: 67300 | E155: =(Assumptions!$B$6-B155)/365.25 -> 44.717317 | F155: =(Assumptions!$B$6-C155)/365.25 -> 15.063655 | G155: =INT(E155) -> 44 | H155: =Assumptions!$B$7-G155 -> 16 | I155: =INT(F155)+IF(F155-INT(F155)>0.5,1,0) -> 15 | J155: =MIN(15/26*D155*I155,Assumptions!$B$10) -> 582403.85 | K155: =IF(F155>=Assumptions!$B$11,1,0) -> 1 | L155: =SUMPRODUCT(Benefit_Grid!$C155:$AU155*(F155/(F155+Benefit_Grid!$C$5:$AU$5))*(1/(1+Assumptions!$B$8))^Benefit_Grid!$C$5:$AU$5) -> 410715.84 | M155: =SUMPRODUCT(Benefit_Grid!$C155:$AU155/(F155+Benefit_Grid!$C$5:$AU$5)*(1/(1+Assumptions!$B$8))^Benefit_Grid!$C$5:$AU$5) -> 27265.351 | N155: 410715.84 | O155: =L155-N155 -> 2.7823262e-08

Sheet Decrements
A1: Decrement table by age
A2: q = death probability, w = withdrawal probability. Combined so the two do not double count: death = q(1 - w/2), withdrawal = w(1 - q/2). L = probability of still being in service at the start of that age, starting from 1 at age 18.
A5: Age | B5: q (death) | C5: w (withdrawal) | D5: Death decrement | E5: Withdrawal decrement | F5: Stay in service | G5: In service at start of age (L)
A6: 18 | B6: =1-EXP(-(Assumptions!$B$12+Assumptions!$B$13*Assumptions!$B$14^A6*(Assumptions!$B$14-1)/LN(Assumptions!$B$14))) -> 0.00051653651 | C6: =VLOOKUP(A6,Assumptions!$A$19:$C$27,3,TRUE()) -> 0.2 | D6: =B6*(1-C6/2) -> 0.00046488286 | E6: =C6*(1-B6/2) -> 0.19994835 | F6: =1-D6-E6 -> 0.79958677 | G6: 1
A7: =A6+1 -> 19 | B7: =1-EXP(-(Assumptions!$B$12+Assumptions!$B$13*Assumptions!$B$14^A7*(Assumptions!$B$14-1)/LN(Assumptions!$B$14))) -> 0.00052819741 | C7: =VLOOKUP(A7,Assumptions!$A$19:$C$27,3,TRUE()) -> 0.2 | D7: =B7*(1-C7/2) -> 0.00047537767 | E7: =C7*(1-B7/2) -> 0.19994718 | F7: =1-D7-E7 -> 0.79957744 | G7: =G6*F6 -> 0.79958677
A8: =A7+1 -> 20 | B8: =1-EXP(-(Assumptions!$B$12+Assumptions!$B$13*Assumptions!$B$14^A8*(Assumptions!$B$14-1)/LN(Assumptions!$B$14))) -> 0.00054102424 | C8: =VLOOKUP(A8,Assumptions!$A$19:$C$27,3,TRUE()) -> 0.2 | D8: =B8*(1-C8/2) -> 0.00048692182 | E8: =C8*(1-B8/2) -> 0.1999459 | F8: =1-D8-E8 -> 0.79956718 | G8: =G7*F7 -> 0.63933154
A9: =A8+1 -> 21 | B9: =1-EXP(-(Assumptions!$B$12+Assumptions!$B$13*Assumptions!$B$14^A9*(Assumptions!$B$14-1)/LN(Assumptions!$B$14))) -> 0.00055513357 | C9: =VLOOKUP(A9,Assumptions!$A$19:$C$27,3,TRUE()) -> 0.2 | D9: =B9*(1-C9/2) -> 0.00049962021 | E9: =C9*(1-B9/2) -> 0.19994449 | F9: =1-D9-E9 -> 0.79955589 | G9: =G8*F8 -> 0.51118852
A10: =A9+1 -> 22 | B10: =1-EXP(-(Assumptions!$B$12+Assumptions!$B$13*Assumptions!$B$14^A10*(Assumptions!$B$14-1)/LN(Assumptions!$B$14))) -> 0.0005706536 | C10: =VLOOKUP(A10,Assumptions!$A$19:$C$27,3,TRUE()) -> 0.2 | D10: =B10*(1-C10/2) -> 0.00051358824 | E10: =C10*(1-B10/2) -> 0.19994293 | F10: =1-D10-E10 -> 0.79954348 | G10: =G9*F9 -> 0.40872379
A11: =A10+1 -> 23 | B11: =1-EXP(-(Assumptions!$B$12+Assumptions!$B$13*Assumptions!$B$14^A11*(Assumptions!$B$14-1)/LN(Assumptions!$B$14))) -> 0.00058772536 | C11: =VLOOKUP(A11,Assumptions!$A$19:$C$27,3,TRUE()) -> 0.2 | D11: =B11*(1-C11/2) -> 0.00052895282 | E11: =C11*(1-B11/2) -> 0.19994123 | F11: =1-D11-E11 -> 0.79952982 | G11: =G10*F10 -> 0.32679244
A12: =A11+1 -> 24 | B12: =1-EXP(-(Assumptions!$B$12+Assumptions!$B$13*Assumptions!$B$14^A12*(Assumptions!$B$14-1)/LN(Assumptions!$B$14))) -> 0.00060650395 | C12: =VLOOKUP(A12,Assumptions!$A$19:$C$27,3,TRUE()) -> 0.2 | D12: =B12*(1-C12/2) -> 0.00054585355 | E12: =C12*(1-B12/2) -> 0.19993935 | F12: =1-D12-E12 -> 0.7995148 | G12: =G11*F11 -> 0.2612803
A13: =A12+1 -> 25 | B13: =1-EXP(-(Assumptions!$B$12+Assumptions!$B$13*Assumptions!$B$14^A13*(Assumptions!$B$14-1)/LN(Assumptions!$B$14))) -> 0.00062715999 | C13: =VLOOKUP(A13,Assumptions!$A$19:$C$27,3,TRUE()) -> 0.15 | D13: =B13*(1-C13/2) -> 0.00058012299 | E13: =C13*(1-B13/2) -> 0.14995296 | F13: =1-D13-E13 -> 0.84946691 | G13: =G12*F12 -> 0.20889747
A14: =A13+1 -> 26 | B14: =1-EXP(-(Assumptions!$B$12+Assumptions!$B$13*Assumptions!$B$14^A14*(Assumptions!$B$14-1)/LN(Assumptions!$B$14))) -> 0.00064988115 | C14: =VLOOKUP(A14,Assumptions!$A$19:$C$27,3,TRUE()) -> 0.15 | D14: =B14*(1-C14/2) -> 0.00060114006 | E14: =C14*(1-B14/2) -> 0.14995126 | F14: =1-D14-E14 -> 0.8494476 | G14: =G13*F13 -> 0.17745149
A15: =A14+1 -> 27 | B15: =1-EXP(-(Assumptions!$B$12+Assumptions!$B$13*Assumptions!$B$14^A15*(Assumptions!$B$14-1)/LN(Assumptions!$B$14))) -> 0.00067487383 | C15: =VLOOKUP(A15,Assumptions!$A$19:$C$27,3,TRUE()) -> 0.15 | D15: =B15*(1-C15/2) -> 0.00062425829 | E15: =C15*(1-B15/2) -> 0.14994938 | F15: =1-D15-E15 -> 0.84942636 | G15: =G14*F14 -> 0.15073574
A16: =A15+1 -> 28 | B16: =1-EXP(-(Assumptions!$B$12+Assumptions!$B$13*Assumptions!$B$14^A16*(Assumptions!$B$14-1)/LN(Assumptions!$B$14))) -> 0.00070236505 | C16: =VLOOKUP(A16,Assumptions!$A$19:$C$27,3,TRUE()) -> 0.15 | D16: =B16*(1-C16/2) -> 0.00064968767 | E16: =C16*(1-B16/2) -> 0.14994732 | F16: =1-D16-E16 -> 0.84940299 | G16: =G15*F15 -> 0.12803891
A17: =A16+1 -> 29 | B17: =1-EXP(-(Assumptions!$B$12+Assumptions!$B$13*Assumptions!$B$14^A17*(Assumptions!$B$14-1)/LN(Assumptions!$B$14))) -> 0.00073260452 | C17: =VLOOKUP(A17,Assumptions!$A$19:$C$27,3,TRUE()) -> 0.15 | D17: =B17*(1-C17/2) -> 0.00067765918 | E17: =C17*(1-B17/2) -> 0.14994505 | F17: =1-D17-E17 -> 0.84937729 | G17: =G16*F16 -> 0.10875663
A18: =A17+1 -> 30 | B18: =1-EXP(-(Assumptions!$B$12+Assumptions!$B$13*Assumptions!$B$14^A18*(Assumptions!$B$14-1)/LN(Assumptions!$B$14))) -> 0.00076586688 | C18: =VLOOKUP(A18,Assumptions!$A$19:$C$27,3,TRUE()) -> 0.11 | D18: =B18*(1-C18/2) -> 0.0007237442 | E18: =C18*(1-B18/2) -> 0.10995788 | F18: =1-D18-E18 -> 0.88931838 | G18: =G17*F17 -> 0.092375415
... A58: =A57+1 -> 70 | B58: =1-EXP(-(Assumptions!$B$12+Assumptions!$B$13*Assumptions!$B$14^A58*(Assumptions!$B$14-1)/LN(Assumptions!$B$14))) -> 0.016828927 | C58: =VLOOKUP(A58,Assumptions!$A$19:$C$27,3,TRUE()) -> 0 | D58: =B58*(1-C58/2) -> 0.016828927 | E58: =C58*(1-B58/2) -> 0 | F58: =1-D58-E58 -> 0.98317107 | G58: =G57*F57 -> 0.016251678

Sheet Benefit_Grid
A1: Expected benefit payable at the end of each future year (Rs), before attribution and discounting
A2: Each cell = P(paid in year t) x benefit at exit, with the part-year rule, wage growth, ceiling, and the five-year rule for withdrawals. Death and retirement are paid regardless of service length.
A3: Row numbers match the Census sheet. Columns are years from the valuation date (t).
A5: Emp ID | B5: Years to retirement | C5: 1 | D5: =C5+1 -> 2 | E5: =D5+1 -> 3 | F5: =E5+1 -> 4 | G5: =F5+1 -> 5 | H5: =G5+1 -> 6 | I5: =H5+1 -> 7 | J5: =I5+1 -> 8 | K5: =J5+1 -> 9 | ... AU5: =AT5+1 -> 45
A6: =Census!A6 -> E001 | B6: =Census!H6 -> 30 | C6: =IF(C$5>$B6,0,INDEX(Decrements!$G$6:$G$58,Census!$G6+C$5-18)/INDEX(Decrements!$G$6:$G$58,Census!$G6-17)*(INDEX(Decrements!$D$6:$D$58,Census!$G6+C$5-18)+IF(C$5=$B6,INDEX(Decrements!$F$6:$F$58,Census!$G6+C$5-18),0)+INDEX(Decrements!$E$6:$E$58,Census!$G6+C$5-18)*IF((Census!$F6+C$5)>=Assumptions!$B$11,1,0))*MIN(15/26*Census!$D6*(1+Assumptions!$B$9)^C$5*(INT((Census!$F6+C$5))+IF((Census!$F6+C$5)-INT((Census!$F6+C$5))>0.5,1,0)),Assumptions!$B$10)) -> 42.7499 | D6: =IF(D$5>$B6,0,INDEX(Decrements!$G$6:$G$58,Census!$G6+D$5-18)/INDEX(Decrements!$G$6:$G$58,Census!$G6-17)*(INDEX(Decrements!$D$6:$D$58,Census!$G6+D$5-18)+IF(D$5=$B6,INDEX(Decrements!$F$6:$F$58,Census!$G6+D$5-18),0)+INDEX(Decrements!$E$6:$E$58,Census!$G6+D$5-18)*IF((Census!$F6+D$5)>=Assumptions!$B$11,1,0))*MIN(15/26*Census!$D6*(1+Assumptions!$B$9)^D$5*(INT((Census!$F6+D$5))+IF((Census!$F6+D$5)-INT((Census!$F6+D$5))>0.5,1,0)),Assumptions!$B$10)) -> 7851.3494 | E6: =IF(E$5>$B6,0,INDEX(Decrements!$G$6:$G$58,Census!$G6+E$5-18)/INDEX(Decrements!$G$6:$G$58,Census!$G6-17)*(INDEX(Decrements!$D$6:$D$58,Census!$G6+E$5-18)+IF(E$5=$B6,INDEX(Decrements!$F$6:$F$58,Census!$G6+E$5-18),0)+INDEX(Decrements!$E$6:$E$58,Census!$G6+E$5-18)*IF((Census!$F6+E$5)>=Assumptions!$B$11,1,0))*MIN(15/26*Census!$D6*(1+Assumptions!$B$9)^E$5*(INT((Census!$F6+E$5))+IF((Census!$F6+E$5)-INT((Census!$F6+E$5))>0.5,1,0)),Assumptions!$B$10)) -> 9051.7208 | F6: =IF(F$5>$B6,0,INDEX(Decrements!$G$6:$G$58,Census!$G6+F$5-18)/INDEX(Decrements!$G$6:$G$58,Census!$G6-17)*(INDEX(Decrements!$D$6:$D$58,Census!$G6+F$5-18)+IF(F$5=$B6,INDEX(Decrements!$F$6:$F$58,Census!$G6+F$5-18),0)+INDEX(Decrements!$E$6:$E$58,Census!$G6+F$5-18)*IF((Census!$F6+F$5)>=Assumptions!$B$11,1,0))*MIN(15/26*Census!$D6*(1+Assumptions!$B$9)^F$5*(INT((Census!$F6+F$5))+IF((Census!$F6+F$5)-INT((Census!$F6+F$5))>0.5,1,0)),Assumptions!$B$10)) -> 10145.654 | G6: =IF(G$5>$B6,0,INDEX(Decrements!$G$6:$G$58,Census!$G6+G$5-18)/INDEX(Decrements!$G$6:$G$58,Census!$G6-17)*(INDEX(Decrements!$D$6:$D$58,Census!$G6+G$5-18)+IF(G$5=$B6,INDEX(Decrements!$F$6:$F$58,Census!$G6+G$5-18),0)+INDEX(Decrements!$E$6:$E$58,Census!$G6+G$5-18)*IF((Census!$F6+G$5)>=Assumptions!$B$11,1,0))*MIN(15/26*Census!$D6*(1+Assumptions!$B$9)^G$5*(INT((Census!$F6+G$5))+IF((Census!$F6+G$5)-INT((Census!$F6+G$5))>0.5,1,0)),Assumptions!$B$10)) -> 11139.616 | H6: =IF(H$5>$B6,0,INDEX(Decrements!$G$6:$G$58,Census!$G6+H$5-18)/INDEX(Decrements!$G$6:$G$58,Census!$G6-17)*(INDEX(Decrements!$D$6:$D$58,Census!$G6+H$5-18)+IF(H$5=$B6,INDEX(Decrements!$F$6:$F$58,Census!$G6+H$5-18),0)+INDEX(Decrements!$E$6:$E$58,Census!$G6+H$5-18)*IF((Census!$F6+H$5)>=Assumptions!$B$11,1,0))*MIN(15/26*Census!$D6*(1+Assumptions!$B$9)^H$5*(INT((Census!$F6+H$5))+IF((Census!$F6+H$5)-INT((Census!$F6+H$5))>0.5,1,0)),Assumptions!$B$10)) -> 8785.4603 | I6: =IF(I$5>$B6,0,INDEX(Decrements!$G$6:$G$58,Census!$G6+I$5-18)/INDEX(Decrements!$G$6:$G$58,Census!$G6-17)*(INDEX(Decrements!$D$6:$D$58,Census!$G6+I$5-18)+IF(I$5=$B6,INDEX(Decrements!$F$6:$F$58,Census!$G6+I$5-18),0)+INDEX(Decrements!$E$6:$E$58,Census!$G6+I$5-18)*IF((Census!$F6+I$5)>=Assumptions!$B$11,1,0))*MIN(15/26*Census!$D6*(1+Assumptions!$B$9)^I$5*(INT((Census!$F6+I$5))+IF((Census!$F6+I$5)-INT((Census!$F6+I$5))>0.5,1,0)),Assumptions!$B$10)) -> 9696.0442 | J6: =IF(J$5>$B6,0,INDEX(Decrements!$G$6:$G$58,Census!$G6+J$5-18)/INDEX(Decrements!$G$6:$G$58,Census!$G6-17)*(INDEX(Decrements!$D$6:$D$58,Census!$G6+J$5-18)+IF(J$5=$B6,INDEX(Decrements!$F$6:$F$58,Census!$G6+J$5-18),0)+INDEX(Decrements!$E$6:$E$58,Census!$G6+J$5-18)*IF((Census!$F6+J$5)>=Assumptions!$B$11,1,0))*MIN(15/26*Census!$D6*(1+Assumptions!$B$9)^J$5*(INT((Census!$F6+J$5))+IF((Census!$F6+J$5)-INT((Census!$F6+J$5))>0.5,1,0)),Assumptions!$B$10)) -> 10594.076 | ... AU6: =IF(AU$5>$B6,0,INDEX(Decrements!$G$6:$G$58,Census!$G6+AU$5-18)/INDEX(Decrements!$G$6:$G$58,Census!$G6-17)*(INDEX(Decrements!$D$6:$D$58,Census!$G6+AU$5-18)+IF(AU$5=$B6,INDEX(Decrements!$F$6:$F$58,Census!$G6+AU$5-18),0)+INDEX(Decrements!$E$6:$E$58,Census!$G6+AU$5-18)*IF((Census!$F6+AU$5)>=Assumptions!$B$11,1,0))*MIN(15/26*Census!$D6*(1+Assumptions!$B$9)^AU$5*(INT((Census!$F6+AU$5))+IF((Census!$F6+AU$5)-INT((Census!$F6+AU$5))>0.5,1,0)),Assumptions!$B$10)) -> 0
A7: =Census!A7 -> E002 | B7: =Census!H7 -> 27 | C7: =IF(C$5>$B7,0,INDEX(Decrements!$G$6:$G$58,Census!$G7+C$5-18)/INDEX(Decrements!$G$6:$G$58,Census!$G7-17)*(INDEX(Decrements!$D$6:$D$58,Census!$G7+C$5-18)+IF(C$5=$B7,INDEX(Decrements!$F$6:$F$58,Census!$G7+C$5-18),0)+INDEX(Decrements!$E$6:$E$58,Census!$G7+C$5-18)*IF((Census!$F7+C$5)>=Assumptions!$B$11,1,0))*MIN(15/26*Census!$D7*(1+Assumptions!$B$9)^C$5*(INT((Census!$F7+C$5))+IF((Census!$F7+C$5)-INT((Census!$F7+C$5))>0.5,1,0)),Assumptions!$B$10)) -> 69.981805 | D7: =IF(D$5>$B7,0,INDEX(Decrements!$G$6:$G$58,Census!$G7+D$5-18)/INDEX(Decrements!$G$6:$G$58,Census!$G7-17)*(INDEX(Decrements!$D$6:$D$58,Census!$G7+D$5-18)+IF(D$5=$B7,INDEX(Decrements!$F$6:$F$58,Census!$G7+D$5-18),0)+INDEX(Decrements!$E$6:$E$58,Census!$G7+D$5-18)*IF((Census!$F7+D$5)>=Assumptions!$B$11,1,0))*MIN(15/26*Census!$D7*(1+Assumptions!$B$9)^D$5*(INT((Census!$F7+D$5))+IF((Census!$F7+D$5)-INT((Census!$F7+D$5))>0.5,1,0)),Assumptions!$B$10)) -> 88.620355 | E7: =IF(E$5>$B7,0,INDEX(Decrements!$G$6:$G$58,Census!$G7+E$5-18)/INDEX(Decrements!$G$6:$G$58,Census!$G7-17)*(INDEX(Decrements!$D$6:$D$58,Census!$G7+E$5-18)+IF(E$5=$B7,INDEX(Decrements!$F$6:$F$58,Census!$G7+E$5-18),0)+INDEX(Decrements!$E$6:$E$58,Census!$G7+E$5-18)*IF((Census!$F7+E$5)>=Assumptions!$B$11,1,0))*MIN(15/26*Census!$D7*(1+Assumptions!$B$9)^E$5*(INT((Census!$F7+E$5))+IF((Census!$F7+E$5)-INT((Census!$F7+E$5))>0.5,1,0)),Assumptions!$B$10)) -> 9344.9278 | F7: =IF(F$5>$B7,0,INDEX(Decrements!$G$6:$G$58,Census!$G7+F$5-18)/INDEX(Decrements!$G$6:$G$58,Census!$G7-17)*(INDEX(Decrements!$D$6:$D$58,Census!$G7+F$5-18)+IF(F$5=$B7,INDEX(Decrements!$F$6:$F$58,Census!$G7+F$5-18),0)+INDEX(Decrements!$E$6:$E$58,Census!$G7+F$5-18)*IF((Census!$F7+F$5)>=Assumptions!$B$11,1,0))*MIN(15/26*Census!$D7*(1+Assumptions!$B$9)^F$5*(INT((Census!$F7+F$5))+IF((Census!$F7+F$5)-INT((Census!$F7+F$5))>0.5,1,0)),Assumptions!$B$10)) -> 10829.174 | G7: =IF(G$5>$B7,0,INDEX(Decrements!$G$6:$G$58,Census!$G7+G$5-18)/INDEX(Decrements!$G$6:$G$58,Census!$G7-17)*(INDEX(Decrements!$D$6:$D$58,Census!$G7+G$5-18)+IF(G$5=$B7,INDEX(Decrements!$F$6:$F$58,Census!$G7+G$5-18),0)+INDEX(Decrements!$E$6:$E$58,Census!$G7+G$5-18)*IF((Census!$F7+G$5)>=Assumptions!$B$11,1,0))*MIN(15/26*Census!$D7*(1+Assumptions!$B$9)^G$5*(INT((Census!$F7+G$5))+IF((Census!$F7+G$5)-INT((Census!$F7+G$5))>0.5,1,0)),Assumptions!$B$10)) -> 12293.147 | H7: =IF(H$5>$B7,0,INDEX(Decrements!$G$6:$G$58,Census!$G7+H$5-18)/INDEX(Decrements!$G$6:$G$58,Census!$G7-17)*(INDEX(Decrements!$D$6:$D$58,Census!$G7+H$5-18)+IF(H$5=$B7,INDEX(Decrements!$F$6:$F$58,Census!$G7+H$5-18),0)+INDEX(Decrements!$E$6:$E$58,Census!$G7+H$5-18)*IF((Census!$F7+H$5)>=Assumptions!$B$11,1,0))*MIN(15/26*Census!$D7*(1+Assumptions!$B$9)^H$5*(INT((Census!$F7+H$5))+IF((Census!$F7+H$5)-INT((Census!$F7+H$5))>0.5,1,0)),Assumptions!$B$10)) -> 13737.094 | I7: =IF(I$5>$B7,0,INDEX(Decrements!$G$6:$G$58,Census!$G7+I$5-18)/INDEX(Decrements!$G$6:$G$58,Census!$G7-17)*(INDEX(Decrements!$D$6:$D$58,Census!$G7+I$5-18)+IF(I$5=$B7,INDEX(Decrements!$F$6:$F$58,Census!$G7+I$5-18),0)+INDEX(Decrements!$E$6:$E$58,Census!$G7+I$5-18)*IF((Census!$F7+I$5)>=Assumptions!$B$11,1,0))*MIN(15/26*Census!$D7*(1+Assumptions!$B$9)^I$5*(INT((Census!$F7+I$5))+IF((Census!$F7+I$5)-INT((Census!$F7+I$5))>0.5,1,0)),Assumptions!$B$10)) -> 15161.266 | J7: =IF(J$5>$B7,0,INDEX(Decrements!$G$6:$G$58,Census!$G7+J$5-18)/INDEX(Decrements!$G$6:$G$58,Census!$G7-17)*(INDEX(Decrements!$D$6:$D$58,Census!$G7+J$5-18)+IF(J$5=$B7,INDEX(Decrements!$F$6:$F$58,Census!$G7+J$5-18),0)+INDEX(Decrements!$E$6:$E$58,Census!$G7+J$5-18)*IF((Census!$F7+J$5)>=Assumptions!$B$11,1,0))*MIN(15/26*Census!$D7*(1+Assumptions!$B$9)^J$5*(INT((Census!$F7+J$5))+IF((Census!$F7+J$5)-INT((Census!$F7+J$5))>0.5,1,0)),Assumptions!$B$10)) -> 10456.834 | ... AU7: =IF(AU$5>$B7,0,INDEX(Decrements!$G$6:$G$58,Census!$G7+AU$5-18)/INDEX(Decrements!$G$6:$G$58,Census!$G7-17)*(INDEX(Decrements!$D$6:$D$58,Census!$G7+AU$5-18)+IF(AU$5=$B7,INDEX(Decrements!$F$6:$F$58,Census!$G7+AU$5-18),0)+INDEX(Decrements!$E$6:$E$58,Census!$G7+AU$5-18)*IF((Census!$F7+AU$5)>=Assumptions!$B$11,1,0))*MIN(15/26*Census!$D7*(1+Assumptions!$B$9)^AU$5*(INT((Census!$F7+AU$5))+IF((Census!$F7+AU$5)-INT((Census!$F7+AU$5))>0.5,1,0)),Assumptions!$B$10)) -> 0
A8: =Census!A8 -> E003 | B8: =Census!H8 -> 21 | C8: =IF(C$5>$B8,0,INDEX(Decrements!$G$6:$G$58,Census!$G8+C$5-18)/INDEX(Decrements!$G$6:$G$58,Census!$G8-17)*(INDEX(Decrements!$D$6:$D$58,Census!$G8+C$5-18)+IF(C$5=$B8,INDEX(Decrements!$F$6:$F$58,Census!$G8+C$5-18),0)+INDEX(Decrements!$E$6:$E$58,Census!$G8+C$5-18)*IF((Census!$F8+C$5)>=Assumptions!$B$11,1,0))*MIN(15/26*Census!$D8*(1+Assumptions!$B$9)^C$5*(INT((Census!$F8+C$5))+IF((Census!$F8+C$5)-INT((Census!$F8+C$5))>0.5,1,0)),Assumptions!$B$10)) -> 75399.734 | D8: =IF(D$5>$B8,0,INDEX(Decrements!$G$6:$G$58,Census!$G8+D$5-18)/INDEX(Decrements!$G$6:$G$58,Census!$G8-17)*(INDEX(Decrements!$D$6:$D$58,Census!$G8+D$5-18)+IF(D$5=$B8,INDEX(Decrements!$F$6:$F$58,Census!$G8+D$5-18),0)+INDEX(Decrements!$E$6:$E$58,Census!$G8+D$5-18)*IF((Census!$F8+D$5)>=Assumptions!$B$11,1,0))*MIN(15/26*Census!$D8*(1+Assumptions!$B$9)^D$5*(INT((Census!$F8+D$5))+IF((Census!$F8+D$5)-INT((Census!$F8+D$5))>0.5,1,0)),Assumptions!$B$10)) -> 50427.866 | E8: =IF(E$5>$B8,0,INDEX(Decrements!$G$6:$G$58,Census!$G8+E$5-18)/INDEX(Decrements!$G$6:$G$58,Census!$G8-17)*(INDEX(Decrements!$D$6:$D$58,Census!$G8+E$5-18)+IF(E$5=$B8,INDEX(Decrements!$F$6:$F$58,Census!$G8+E$5-18),0)+INDEX(Decrements!$E$6:$E$58,Census!$G8+E$5-18)*IF((Census!$F8+E$5)>=Assumptions!$B$11,1,0))*MIN(15/26*Census!$D8*(1+Assumptions!$B$9)^E$5*(INT((Census!$F8+E$5))+IF((Census!$F8+E$5)-INT((Census!$F8+E$5))>0.5,1,0)),Assumptions!$B$10)) -> 54994.982 | F8: =IF(F$5>$B8,0,INDEX(Decrements!$G$6:$G$58,Census!$G8+F$5-18)/INDEX(Decrements!$G$6:$G$58,Census!$G8-17)*(INDEX(Decrements!$D$6:$D$58,Census!$G8+F$5-18)+IF(F$5=$B8,INDEX(Decrements!$F$6:$F$58,Census!$G8+F$5-18),0)+INDEX(Decrements!$E$6:$E$58,Census!$G8+F$5-18)*IF((Census!$F8+F$5)>=Assumptions!$B$11,1,0))*MIN(15/26*Census!$D8*(1+Assumptions!$B$9)^F$5*(INT((Census!$F8+F$5))+IF((Census!$F8+F$5)-INT((Census!$F8+F$5))>0.5,1,0)),Assumptions!$B$10)) -> 59772.794 | G8: =IF(G$5>$B8,0,INDEX(Decrements!$G$6:$G$58,Census!$G8+G$5-18)/INDEX(Decrements!$G$6:$G$58,Census!$G8-17)*(INDEX(Decrements!$D$6:$D$58,Census!$G8+G$5-18)+IF(G$5=$B8,INDEX(Decrements!$F$6:$F$58,Census!$G8+G$5-18),0)+INDEX(Decrements!$E$6:$E$58,Census!$G8+G$5-18)*IF((Census!$F8+G$5)>=Assumptions!$B$11,1,0))*MIN(15/26*Census!$D8*(1+Assumptions!$B$9)^G$5*(INT((Census!$F8+G$5))+IF((Census!$F8+G$5)-INT((Census!$F8+G$5))>0.5,1,0)),Assumptions!$B$10)) -> 64770.6 | H8: =IF(H$5>$B8,0,INDEX(Decrements!$G$6:$G$58,Census!$G8+H$5-18)/INDEX(Decrements!$G$6:$G$58,Census!$G8-17)*(INDEX(Decrements!$D$6:$D$58,Census!$G8+H$5-18)+IF(H$5=$B8,INDEX(Decrements!$F$6:$F$58,Census!$G8+H$5-18),0)+INDEX(Decrements!$E$6:$E$58,Census!$G8+H$5-18)*IF((Census!$F8+H$5)>=Assumptions!$B$11,1,0))*MIN(15/26*Census!$D8*(1+Assumptions!$B$9)^H$5*(INT((Census!$F8+H$5))+IF((Census!$F8+H$5)-INT((Census!$F8+H$5))>0.5,1,0)),Assumptions!$B$10)) -> 69998.25 | I8: =IF(I$5>$B8,0,INDEX(Decrements!$G$6:$G$58,Census!$G8+I$5-18)/INDEX(Decrements!$G$6:$G$58,Census!$G8-17)*(INDEX(Decrements!$D$6:$D$58,Census!$G8+I$5-18)+IF(I$5=$B8,INDEX(Decrements!$F$6:$F$58,Census!$G8+I$5-18),0)+INDEX(Decrements!$E$6:$E$58,Census!$G8+I$5-18)*IF((Census!$F8+I$5)>=Assumptions!$B$11,1,0))*MIN(15/26*Census!$D8*(1+Assumptions!$B$9)^I$5*(INT((Census!$F8+I$5))+IF((Census!$F8+I$5)-INT((Census!$F8+I$5))>0.5,1,0)),Assumptions!$B$10)) -> 44965.612 | J8: =IF(J$5>$B8,0,INDEX(Decrements!$G$6:$G$58,Census!$G8+J$5-18)/INDEX(Decrements!$G$6:$G$58,Census!$G8-17)*(INDEX(Decrements!$D$6:$D$58,Census!$G8+J$5-18)+IF(J$5=$B8,INDEX(Decrements!$F$6:$F$58,Census!$G8+J$5-18),0)+INDEX(Decrements!$E$6:$E$58,Census!$G8+J$5-18)*IF((Census!$F8+J$5)>=Assumptions!$B$11,1,0))*MIN(15/26*Census!$D8*(1+Assumptions!$B$9)^J$5*(INT((Census!$F8+J$5))+IF((Census!$F8+J$5)-INT((Census!$F8+J$5))>0.5,1,0)),Assumptions!$B$10)) -> 43734.818 | ... AU8: =IF(AU$5>$B8,0,INDEX(Decrements!$G$6:$G$58,Census!$G8+AU$5-18)/INDEX(Decrements!$G$6:$G$58,Census!$G8-17)*(INDEX(Decrements!$D$6:$D$58,Census!$G8+AU$5-18)+IF(AU$5=$B8,INDEX(Decrements!$F$6:$F$58,Census!$G8+AU$5-18),0)+INDEX(Decrements!$E$6:$E$58,Census!$G8+AU$5-18)*IF((Census!$F8+AU$5)>=Assumptions!$B$11,1,0))*MIN(15/26*Census!$D8*(1+Assumptions!$B$9)^AU$5*(INT((Census!$F8+AU$5))+IF((Census!$F8+AU$5)-INT((Census!$F8+AU$5))>0.5,1,0)),Assumptions!$B$10)) -> 0
A9: =Census!A9 -> E004 | B9: =Census!H9 -> 21 | C9: =IF(C$5>$B9,0,INDEX(Decrements!$G$6:$G$58,Census!$G9+C$5-18)/INDEX(Decrements!$G$6:$G$58,Census!$G9-17)*(INDEX(Decrements!$D$6:$D$58,Census!$G9+C$5-18)+IF(C$5=$B9,INDEX(Decrements!$F$6:$F$58,Census!$G9+C$5-18),0)+INDEX(Decrements!$E$6:$E$58,Census!$G9+C$5-18)*IF((Census!$F9+C$5)>=Assumptions!$B$11,1,0))*MIN(15/26*Census!$D9*(1+Assumptions!$B$9)^C$5*(INT((Census!$F9+C$5))+IF((Census!$F9+C$5)-INT((Census!$F9+C$5))>0.5,1,0)),Assumptions!$B$10)) -> 15646.33 | D9: =IF(D$5>$B9,0,INDEX(Decrements!$G$6:$G$58,Census!$G9+D$5-18)/INDEX(Decrements!$G$6:$G$58,Census!$G9-17)*(INDEX(Decrements!$D$6:$D$58,Census!$G9+D$5-18)+IF(D$5=$B9,INDEX(Decrements!$F$6:$F$58,Census!$G9+D$5-18),0)+INDEX(Decrements!$E$6:$E$58,Census!$G9+D$5-18)*IF((Census!$F9+D$5)>=Assumptions!$B$11,1,0))*MIN(15/26*Census!$D9*(1+Assumptions!$B$9)^D$5*(INT((Census!$F9+D$5))+IF((Census!$F9+D$5)-INT((Census!$F9+D$5))>0.5,1,0)),Assumptions!$B$10)) -> 11211.829 | E9: =IF(E$5>$B9,0,INDEX(Decrements!$G$6:$G$58,Census!$G9+E$5-18)/INDEX(Decrements!$G$6:$G$58,Census!$G9-17)*(INDEX(Decrements!$D$6:$D$58,Census!$G9+E$5-18)+IF(E$5=$B9,INDEX(Decrements!$F$6:$F$58,Census!$G9+E$5-18),0)+INDEX(Decrements!$E$6:$E$58,Census!$G9+E$5-18)*IF((Census!$F9+E$5)>=Assumptions!$B$11,1,0))*MIN(15/26*Census!$D9*(1+Assumptions!$B$9)^E$5*(INT((Census!$F9+E$5))+IF((Census!$F9+E$5)-INT((Census!$F9+E$5))>0.5,1,0)),Assumptions!$B$10)) -> 12946.505 | F9: =IF(F$5>$B9,0,INDEX(Decrements!$G$6:$G$58,Census!$G9+F$5-18)/INDEX(Decrements!$G$6:$G$58,Census!$G9-17)*(INDEX(Decrements!$D$6:$D$58,Census!$G9+F$5-18)+IF(F$5=$B9,INDEX(Decrements!$F$6:$F$58,Census!$G9+F$5-18),0)+INDEX(Decrements!$E$6:$E$58,Census!$G9+F$5-18)*IF((Census!$F9+F$5)>=Assumptions!$B$11,1,0))*MIN(15/26*Census!$D9*(1+Assumptions!$B$9)^F$5*(INT((Census!$F9+F$5))+IF((Census!$F9+F$5)-INT((Census!$F9+F$5))>0.5,1,0)),Assumptions!$B$10)) -> 14766.138 | G9: =IF(G$5>$B9,0,INDEX(Decrements!$G$6:$G$58,Census!$G9+G$5-18)/INDEX(Decrements!$G$6:$G$58,Census!$G9-17)*(INDEX(Decrements!$D$6:$D$58,Census!$G9+G$5-18)+IF(G$5=$B9,INDEX(Decrements!$F$6:$F$58,Census!$G9+G$5-18),0)+INDEX(Decrements!$E$6:$E$58,Census!$G9+G$5-18)*IF((Census!$F9+G$5)>=Assumptions!$B$11,1,0))*MIN(15/26*Census!$D9*(1+Assumptions!$B$9)^G$5*(INT((Census!$F9+G$5))+IF((Census!$F9+G$5)-INT((Census!$F9+G$5))>0.5,1,0)),Assumptions!$B$10)) -> 16674.503 | H9: =IF(H$5>$B9,0,INDEX(Decrements!$G$6:$G$58,Census!$G9+H$5-18)/INDEX(Decrements!$G$6:$G$58,Census!$G9-17)*(INDEX(Decrements!$D$6:$D$58,Census!$G9+H$5-18)+IF(H$5=$B9,INDEX(Decrements!$F$6:$F$58,Census!$G9+H$5-18),0)+INDEX(Decrements!$E$6:$E$58,Census!$G9+H$5-18)*IF((Census!$F9+H$5)>=Assumptions!$B$11,1,0))*MIN(15/26*Census!$D9*(1+Assumptions!$B$9)^H$5*(INT((Census!$F9+H$5))+IF((Census!$F9+H$5)-INT((Census!$F9+H$5))>0.5,1,0)),Assumptions!$B$10)) -> 18675.59 | I9: =IF(I$5>$B9,0,INDEX(Decrements!$G$6:$G$58,Census!$G9+I$5-18)/INDEX(Decrements!$G$6:$G$58,Census!$G9-17)*(INDEX(Decrements!$D$6:$D$58,Census!$G9+I$5-18)+IF(I$5=$B9,INDEX(Decrements!$F$6:$F$58,Census!$G9+I$5-18),0)+INDEX(Decrements!$E$6:$E$58,Census!$G9+I$5-18)*IF((Census!$F9+I$5)>=Assumptions!$B$11,1,0))*MIN(15/26*Census!$D9*(1+Assumptions!$B$9)^I$5*(INT((Census!$F9+I$5))+IF((Census!$F9+I$5)-INT((Census!$F9+I$5))>0.5,1,0)),Assumptions!$B$10)) -> 12773.218 | J9: =IF(J$5>$B9,0,INDEX(Decrements!$G$6:$G$58,Census!$G9+J$5-18)/INDEX(Decrements!$G$6:$G$58,Census!$G9-17)*(INDEX(Decrements!$D$6:$D$58,Census!$G9+J$5-18)+IF(J$5=$B9,INDEX(Decrements!$F$6:$F$58,Census!$G9+J$5-18),0)+INDEX(Decrements!$E$6:$E$58,Census!$G9+J$5-18)*IF((Census!$F9+J$5)>=Assumptions!$B$11,1,0))*MIN(15/26*Census!$D9*(1+Assumptions!$B$9)^J$5*(INT((Census!$F9+J$5))+IF((Census!$F9+J$5)-INT((Census!$F9+J$5))>0.5,1,0)),Assumptions!$B$10)) -> 14449.592 | ... AU9: =IF(AU$5>$B9,0,INDEX(Decrements!$G$6:$G$58,Census!$G9+AU$5-18)/INDEX(Decrements!$G$6:$G$58,Census!$G9-17)*(INDEX(Decrements!$D$6:$D$58,Census!$G9+AU$5-18)+IF(AU$5=$B9,INDEX(Decrements!$F$6:$F$58,Census!$G9+AU$5-18),0)+INDEX(Decrements!$E$6:$E$58,Census!$G9+AU$5-18)*IF((Census!$F9+AU$5)>=Assumptions!$B$11,1,0))*MIN(15/26*Census!$D9*(1+Assumptions!$B$9)^AU$5*(INT((Census!$F9+AU$5))+IF((Census!$F9+AU$5)-INT((Census!$F9+AU$5))>0.5,1,0)),Assumptions!$B$10)) -> 0
A10: =Census!A10 -> E005 | B10: =Census!H10 -> 25 | C10: =IF(C$5>$B10,0,INDEX(Decrements!$G$6:$G$58,Census!$G10+C$5-18)/INDEX(Decrements!$G$6:$G$58,Census!$G10-17)*(INDEX(Decrements!$D$6:$D$58,Census!$G10+C$5-18)+IF(C$5=$B10,INDEX(Decrements!$F$6:$F$58,Census!$G10+C$5-18),0)+INDEX(Decrements!$E$6:$E$58,Census!$G10+C$5-18)*IF((Census!$F10+C$5)>=Assumptions!$B$11,1,0))*MIN(15/26*Census!$D10*(1+Assumptions!$B$9)^C$5*(INT((Census!$F10+C$5))+IF((Census!$F10+C$5)-INT((Census!$F10+C$5))>0.5,1,0)),Assumptions!$B$10)) -> 24702.469 | D10: =IF(D$5>$B10,0,INDEX(Decrements!$G$6:$G$58,Census!$G10+D$5-18)/INDEX(Decrements!$G$6:$G$58,Census!$G10-17)*(INDEX(Decrements!$D$6:$D$58,Census!$G10+D$5-18)+IF(D$5=$B10,INDEX(Decrements!$F$6:$F$58,Census!$G10+D$5-18),0)+INDEX(Decrements!$E$6:$E$58,Census!$G10+D$5-18)*IF((Census!$F10+D$5)>=Assumptions!$B$11,1,0))*MIN(15/26*Census!$D10*(1+Assumptions!$B$9)^D$5*(INT((Census!$F10+D$5))+IF((Census!$F10+D$5)-INT((Census!$F10+D$5))>0.5,1,0)),Assumptions!$B$10)) -> 26990.17 | E10: =IF(E$5>$B10,0,INDEX(Decrements!$G$6:$G$58,Census!$G10+E$5-18)/INDEX(Decrements!$G$6:$G$58,Census!$G10-17)*(INDEX(Decrements!$D$6:$D$58,Census!$G10+E$5-18)+IF(E$5=$B10,INDEX(Decrements!$F$6:$F$58,Census!$G10+E$5-18),0)+INDEX(Decrements!$E$6:$E$58,Census!$G10+E$5-18)*IF((Census!$F10+E$5)>=Assumptions!$B$11,1,0))*MIN(15/26*Census!$D10*(1+Assumptions!$B$9)^E$5*(INT((Census!$F10+E$5))+IF((Census!$F10+E$5)-INT((Census!$F10+E$5))>0.5,1,0)),Assumptions!$B$10)) -> 29246.236 | F10: =IF(F$5>$B10,0,INDEX(Decrements!$G$6:$G$58,Census!$G10+F$5-18)/INDEX(Decrements!$G$6:$G$58,Census!$G10-17)*(INDEX(Decrements!$D$6:$D$58,Census!$G10+F$5-18)+IF(F$5=$B10,INDEX(Decrements!$F$6:$F$58,Census!$G10+F$5-18),0)+INDEX(Decrements!$E$6:$E$58,Census!$G10+F$5-18)*IF((Census!$F10+F$5)>=Assumptions!$B$11,1,0))*MIN(15/26*Census!$D10*(1+Assumptions!$B$9)^F$5*(INT((Census!$F10+F$5))+IF((Census!$F10+F$5)-INT((Census!$F10+F$5))>0.5,1,0)),Assumptions!$B$10)) -> 31471.062 | G10: =IF(G$5>$B10,0,INDEX(Decrements!$G$6:$G$58,Census!$G10+G$5-18)/INDEX(Decrements!$G$6:$G$58,Census!$G10-17)*(INDEX(Decrements!$D$6:$D$58,Census!$G10+G$5-18)+IF(G$5=$B10,INDEX(Decrements!$F$6:$F$58,Census!$G10+G$5-18),0)+INDEX(Decrements!$E$6:$E$58,Census!$G10+G$5-18)*IF((Census!$F10+G$5)>=Assumptions!$B$11,1,0))*MIN(15/26*Census!$D10*(1+Assumptions!$B$9)^G$5*(INT((Census!$F10+G$5))+IF((Census!$F10+G$5)-INT((Census!$F10+G$5))>0.5,1,0)),Assumptions!$B$10)) -> 33665.042 | H10: =IF(H$5>$B10,0,INDEX(Decrements!$G$6:$G$58,Census!$G10+H$5-18)/INDEX(Decrements!$G$6:$G$58,Census!$G10-17)*(INDEX(Decrements!$D$6:$D$58,Census!$G10+H$5-18)+IF(H$5=$B10,INDEX(Decrements!$F$6:$F$58,Census!$G10+H$5-18),0)+INDEX(Decrements!$E$6:$E$58,Census!$G10+H$5-18)*IF((Census!$F10+H$5)>=Assumptions!$B$11,1,0))*MIN(15/26*Census!$D10*(1+Assumptions!$B$9)^H$5*(INT((Census!$F10+H$5))+IF((Census!$F10+H$5)-INT((Census!$F10+H$5))>0.5,1,0)),Assumptions!$B$10)) -> 22615.929 | I10: =IF(I$5>$B10,0,INDEX(Decrements!$G$6:$G$58,Census!$G10+I$5-18)/INDEX(Decrements!$G$6:$G$58,Census!$G10-17)*(INDEX(Decrements!$D$6:$D$58,Census!$G10+I$5-18)+IF(I$5=$B10,INDEX(Decrements!$F$6:$F$58,Census!$G10+I$5-18),0)+INDEX(Decrements!$E$6:$E$58,Census!$G10+I$5-18)*IF((Census!$F10+I$5)>=Assumptions!$B$11,1,0))*MIN(15/26*Census!$D10*(1+Assumptions!$B$9)^I$5*(INT((Census!$F10+I$5))+IF((Census!$F10+I$5)-INT((Census!$F10+I$5))>0.5,1,0)),Assumptions!$B$10)) -> 24760.916 | J10: =IF(J$5>$B10,0,INDEX(Decrements!$G$6:$G$58,Census!$G10+J$5-18)/INDEX(Decrements!$G$6:$G$58,Census!$G10-17)*(INDEX(Decrements!$D$6:$D$58,Census!$G10+J$5-18)+IF(J$5=$B10,INDEX(Decrements!$F$6:$F$58,Census!$G10+J$5-18),0)+INDEX(Decrements!$E$6:$E$58,Census!$G10+J$5-18)*IF((Census!$F10+J$5)>=Assumptions!$B$11,1,0))*MIN(15/26*Census!$D10*(1+Assumptions!$B$9)^J$5*(INT((Census!$F10+J$5))+IF((Census!$F10+J$5)-INT((Census!$F10+J$5))>0.5,1,0)),Assumptions!$B$10)) -> 27005.52 | ... AU10: =IF(AU$5>$B10,0,INDEX(Decrements!$G$6:$G$58,Census!$G10+AU$5-18)/INDEX(Decrements!$G$6:$G$58,Census!$G10-17)*(INDEX(Decrements!$D$6:$D$58,Census!$G10+AU$5-18)+IF(AU$5=$B10,INDEX(Decrements!$F$6:$F$58,Census!$G10+AU$5-18),0)+INDEX(Decrements!$E$6:$E$58,Census!$G10+AU$5-18)*IF((Census!$F10+AU$5)>=Assumptions!$B$11,1,0))*MIN(15/26*Census!$D10*(1+Assumptions!$B$9)^AU$5*(INT((Census!$F10+AU$5))+IF((Census!$F10+AU$5)-INT((Census!$F10+AU$5))>0.5,1,0)),Assumptions!$B$10)) -> 0
A11: =Census!A11 -> E006 | B11: =Census!H11 -> 24 | C11: =IF(C$5>$B11,0,INDEX(Decrements!$G$6:$G$58,Census!$G11+C$5-18)/INDEX(Decrements!$G$6:$G$58,Census!$G11-17)*(INDEX(Decrements!$D$6:$D$58,Census!$G11+C$5-18)+IF(C$5=$B11,INDEX(Decrements!$F$6:$F$58,Census!$G11+C$5-18),0)+INDEX(Decrements!$E$6:$E$58,Census!$G11+C$5-18)*IF((Census!$F11+C$5)>=Assumptions!$B$11,1,0))*MIN(15/26*Census!$D11*(1+Assumptions!$B$9)^C$5*(INT((Census!$F11+C$5))+IF((Census!$F11+C$5)-INT((Census!$F11+C$5))>0.5,1,0)),Assumptions!$B$10)) -> 25778.403 | D11: =IF(D$5>$B11,0,INDEX(Decrements!$G$6:$G$58,Census!$G11+D$5-18)/INDEX(Decrements!$G$6:$G$58,Census!$G11-17)*(INDEX(Decrements!$D$6:$D$58,Census!$G11+D$5-18)+IF(D$5=$B11,INDEX(Decrements!$F$6:$F$58,Census!$G11+D$5-18),0)+INDEX(Decrements!$E$6:$E$58,Census!$G11+D$5-18)*IF((Census!$F11+D$5)>=Assumptions!$B$11,1,0))*MIN(15/26*Census!$D11*(1+Assumptions!$B$9)^D$5*(INT((Census!$F11+D$5))+IF((Census!$F11+D$5)-INT((Census!$F11+D$5))>0.5,1,0)),Assumptions!$B$10)) -> 28165.955 | E11: =IF(E$5>$B11,0,INDEX(Decrements!$G$6:$G$58,Census!$G11+E$5-18)/INDEX(Decrements!$G$6:$G$58,Census!$G11-17)*(INDEX(Decrements!$D$6:$D$58,Census!$G11+E$5-18)+IF(E$5=$B11,INDEX(Decrements!$F$6:$F$58,Census!$G11+E$5-18),0)+INDEX(Decrements!$E$6:$E$58,Census!$G11+E$5-18)*IF((Census!$F11+E$5)>=Assumptions!$B$11,1,0))*MIN(15/26*Census!$D11*(1+Assumptions!$B$9)^E$5*(INT((Census!$F11+E$5))+IF((Census!$F11+E$5)-INT((Census!$F11+E$5))>0.5,1,0)),Assumptions!$B$10)) -> 30520.549 | F11: =IF(F$5>$B11,0,INDEX(Decrements!$G$6:$G$58,Census!$G11+F$5-18)/INDEX(Decrements!$G$6:$G$58,Census!$G11-17)*(INDEX(Decrements!$D$6:$D$58,Census!$G11+F$5-18)+IF(F$5=$B11,INDEX(Decrements!$F$6:$F$58,Census!$G11+F$5-18),0)+INDEX(Decrements!$E$6:$E$58,Census!$G11+F$5-18)*IF((Census!$F11+F$5)>=Assumptions!$B$11,1,0))*MIN(15/26*Census!$D11*(1+Assumptions!$B$9)^F$5*(INT((Census!$F11+F$5))+IF((Census!$F11+F$5)-INT((Census!$F11+F$5))>0.5,1,0)),Assumptions!$B$10)) -> 32842.6 | G11: =IF(G$5>$B11,0,INDEX(Decrements!$G$6:$G$58,Census!$G11+G$5-18)/INDEX(Decrements!$G$6:$G$58,Census!$G11-17)*(INDEX(Decrements!$D$6:$D$58,Census!$G11+G$5-18)+IF(G$5=$B11,INDEX(Decrements!$F$6:$F$58,Census!$G11+G$5-18),0)+INDEX(Decrements!$E$6:$E$58,Census!$G11+G$5-18)*IF((Census!$F11+G$5)>=Assumptions!$B$11,1,0))*MIN(15/26*Census!$D11*(1+Assumptions!$B$9)^G$5*(INT((Census!$F11+G$5))+IF((Census!$F11+G$5)-INT((Census!$F11+G$5))>0.5,1,0)),Assumptions!$B$10)) -> 22176.565 | H11: =IF(H$5>$B11,0,INDEX(Decrements!$G$6:$G$58,Census!$G11+H$5-18)/INDEX(Decrements!$G$6:$G$58,Census!$G11-17)*(INDEX(Decrements!$D$6:$D$58,Census!$G11+H$5-18)+IF(H$5=$B11,INDEX(Decrements!$F$6:$F$58,Census!$G11+H$5-18),0)+INDEX(Decrements!$E$6:$E$58,Census!$G11+H$5-18)*IF((Census!$F11+H$5)>=Assumptions!$B$11,1,0))*MIN(15/26*Census!$D11*(1+Assumptions!$B$9)^H$5*(INT((Census!$F11+H$5))+IF((Census!$F11+H$5)-INT((Census!$F11+H$5))>0.5,1,0)),Assumptions!$B$10)) -> 24388.272 | I11: =IF(I$5>$B11,0,INDEX(Decrements!$G$6:$G$58,Census!$G11+I$5-18)/INDEX(Decrements!$G$6:$G$58,Census!$G11-17)*(INDEX(Decrements!$D$6:$D$58,Census!$G11+I$5-18)+IF(I$5=$B11,INDEX(Decrements!$F$6:$F$58,Census!$G11+I$5-18),0)+INDEX(Decrements!$E$6:$E$58,Census!$G11+I$5-18)*IF((Census!$F11+I$5)>=Assumptions!$B$11,1,0))*MIN(15/26*Census!$D11*(1+Assumptions!$B$9)^I$5*(INT((Census!$F11+I$5))+IF((Census!$F11+I$5)-INT((Census!$F11+I$5))>0.5,1,0)),Assumptions!$B$10)) -> 26703.406 | J11: =IF(J$5>$B11,0,INDEX(Decrements!$G$6:$G$58,Census!$G11+J$5-18)/INDEX(Decrements!$G$6:$G$58,Census!$G11-17)*(INDEX(Decrements!$D$6:$D$58,Census!$G11+J$5-18)+IF(J$5=$B11,INDEX(Decrements!$F$6:$F$58,Census!$G11+J$5-18),0)+INDEX(Decrements!$E$6:$E$58,Census!$G11+J$5-18)*IF((Census!$F11+J$5)>=Assumptions!$B$11,1,0))*MIN(15/26*Census!$D11*(1+Assumptions!$B$9)^J$5*(INT((Census!$F11+J$5))+IF((Census!$F11+J$5)-INT((Census!$F11+J$5))>0.5,1,0)),Assumptions!$B$10)) -> 29126.538 | ... AU11: =IF(AU$5>$B11,0,INDEX(Decrements!$G$6:$G$58,Census!$G11+AU$5-18)/INDEX(Decrements!$G$6:$G$58,Census!$G11-17)*(INDEX(Decrements!$D$6:$D$58,Census!$G11+AU$5-18)+IF(AU$5=$B11,INDEX(Decrements!$F$6:$F$58,Census!$G11+AU$5-18),0)+INDEX(Decrements!$E$6:$E$58,Census!$G11+AU$5-18)*IF((Census!$F11+AU$5)>=Assumptions!$B$11,1,0))*MIN(15/26*Census!$D11*(1+Assumptions!$B$9)^AU$5*(INT((Census!$F11+AU$5))+IF((Census!$F11+AU$5)-INT((Census!$F11+AU$5))>0.5,1,0)),Assumptions!$B$10)) -> 0
A12: =Census!A12 -> E007 | B12: =Census!H12 -> 25 | C12: =IF(C$5>$B12,0,INDEX(Decrements!$G$6:$G$58,Census!$G12+C$5-18)/INDEX(Decrements!$G$6:$G$58,Census!$G12-17)*(INDEX(Decrements!$D$6:$D$58,Census!$G12+C$5-18)+IF(C$5=$B12,INDEX(Decrements!$F$6:$F$58,Census!$G12+C$5-18),0)+INDEX(Decrements!$E$6:$E$58,Census!$G12+C$5-18)*IF((Census!$F12+C$5)>=Assumptions!$B$11,1,0))*MIN(15/26*Census!$D12*(1+Assumptions!$B$9)^C$5*(INT((Census!$F12+C$5))+IF((Census!$F12+C$5)-INT((Census!$F12+C$5))>0.5,1,0)),Assumptions!$B$10)) -> 25105.775 | D12: =IF(D$5>$B12,0,INDEX(Decrements!$G$6:$G$58,Census!$G12+D$5-18)/INDEX(Decrements!$G$6:$G$58,Census!$G12-17)*(INDEX(Decrements!$D$6:$D$58,Census!$G12+D$5-18)+IF(D$5=$B12,INDEX(Decrements!$F$6:$F$58,Census!$G12+D$5-18),0)+INDEX(Decrements!$E$6:$E$58,Census!$G12+D$5-18)*IF((Census!$F12+D$5)>=Assumptions!$B$11,1,0))*MIN(15/26*Census!$D12*(1+Assumptions!$B$9)^D$5*(INT((Census!$F12+D$5))+IF((Census!$F12+D$5)-INT((Census!$F12+D$5))>0.5,1,0)),Assumptions!$B$10)) -> 27430.826 | E12: =IF(E$5>$B12,0,INDEX(Decrements!$G$6:$G$58,Census!$G12+E$5-18)/INDEX(Decrements!$G$6:$G$58,Census!$G12-17)*(INDEX(Decrements!$D$6:$D$58,Census!$G12+E$5-18)+IF(E$5=$B12,INDEX(Decrements!$F$6:$F$58,Census!$G12+E$5-18),0)+INDEX(Decrements!$E$6:$E$58,Census!$G12+E$5-18)*IF((Census!$F12+E$5)>=Assumptions!$B$11,1,0))*MIN(15/26*Census!$D12*(1+Assumptions!$B$9)^E$5*(INT((Census!$F12+E$5))+IF((Census!$F12+E$5)-INT((Census!$F12+E$5))>0.5,1,0)),Assumptions!$B$10)) -> 29723.726 | F12: =IF(F$5>$B12,0,INDEX(Decrements!$G$6:$G$58,Census!$G12+F$5-18)/INDEX(Decrements!$G$6:$G$58,Census!$G12-17)*(INDEX(Decrements!$D$6:$D$58,Census!$G12+F$5-18)+IF(F$5=$B12,INDEX(Decrements!$F$6:$F$58,Census!$G12+F$5-18),0)+INDEX(Decrements!$E$6:$E$58,Census!$G12+F$5-18)*IF((Census!$F12+F$5)>=Assumptions!$B$11,1,0))*MIN(15/26*Census!$D12*(1+Assumptions!$B$9)^F$5*(INT((Census!$F12+F$5))+IF((Census!$F12+F$5)-INT((Census!$F12+F$5))>0.5,1,0)),Assumptions!$B$10)) -> 31984.875 | G12: =IF(G$5>$B12,0,INDEX(Decrements!$G$6:$G$58,Census!$G12+G$5-18)/INDEX(Decrements!$G$6:$G$58,Census!$G12-17)*(INDEX(Decrements!$D$6:$D$58,Census!$G12+G$5-18)+IF(G$5=$B12,INDEX(Decrements!$F$6:$F$58,Census!$G12+G$5-18),0)+INDEX(Decrements!$E$6:$E$58,Census!$G12+G$5-18)*IF((Census!$F12+G$5)>=Assumptions!$B$11,1,0))*MIN(15/26*Census!$D12*(1+Assumptions!$B$9)^G$5*(INT((Census!$F12+G$5))+IF((Census!$F12+G$5)-INT((Census!$F12+G$5))>0.5,1,0)),Assumptions!$B$10)) -> 34214.675 | H12: =IF(H$5>$B12,0,INDEX(Decrements!$G$6:$G$58,Census!$G12+H$5-18)/INDEX(Decrements!$G$6:$G$58,Census!$G12-17)*(INDEX(Decrements!$D$6:$D$58,Census!$G12+H$5-18)+IF(H$5=$B12,INDEX(Decrements!$F$6:$F$58,Census!$G12+H$5-18),0)+INDEX(Decrements!$E$6:$E$58,Census!$G12+H$5-18)*IF((Census!$F12+H$5)>=Assumptions!$B$11,1,0))*MIN(15/26*Census!$D12*(1+Assumptions!$B$9)^H$5*(INT((Census!$F12+H$5))+IF((Census!$F12+H$5)-INT((Census!$F12+H$5))>0.5,1,0)),Assumptions!$B$10)) -> 22985.169 | I12: =IF(I$5>$B12,0,INDEX(Decrements!$G$6:$G$58,Census!$G12+I$5-18)/INDEX(Decrements!$G$6:$G$58,Census!$G12-17)*(INDEX(Decrements!$D$6:$D$58,Census!$G12+I$5-18)+IF(I$5=$B12,INDEX(Decrements!$F$6:$F$58,Census!$G12+I$5-18),0)+INDEX(Decrements!$E$6:$E$58,Census!$G12+I$5-18)*IF((Census!$F12+I$5)>=Assumptions!$B$11,1,0))*MIN(15/26*Census!$D12*(1+Assumptions!$B$9)^I$5*(INT((Census!$F12+I$5))+IF((Census!$F12+I$5)-INT((Census!$F12+I$5))>0.5,1,0)),Assumptions!$B$10)) -> 25165.175 | J12: =IF(J$5>$B12,0,INDEX(Decrements!$G$6:$G$58,Census!$G12+J$5-18)/INDEX(Decrements!$G$6:$G$58,Census!$G12-17)*(INDEX(Decrements!$D$6:$D$58,Census!$G12+J$5-18)+IF(J$5=$B12,INDEX(Decrements!$F$6:$F$58,Census!$G12+J$5-18),0)+INDEX(Decrements!$E$6:$E$58,Census!$G12+J$5-18)*IF((Census!$F12+J$5)>=Assumptions!$B$11,1,0))*MIN(15/26*Census!$D12*(1+Assumptions!$B$9)^J$5*(INT((Census!$F12+J$5))+IF((Census!$F12+J$5)-INT((Census!$F12+J$5))>0.5,1,0)),Assumptions!$B$10)) -> 27446.426 | ... AU12: =IF(AU$5>$B12,0,INDEX(Decrements!$G$6:$G$58,Census!$G12+AU$5-18)/INDEX(Decrements!$G$6:$G$58,Census!$G12-17)*(INDEX(Decrements!$D$6:$D$58,Census!$G12+AU$5-18)+IF(AU$5=$B12,INDEX(Decrements!$F$6:$F$58,Census!$G12+AU$5-18),0)+INDEX(Decrements!$E$6:$E$58,Census!$G12+AU$5-18)*IF((Census!$F12+AU$5)>=Assumptions!$B$11,1,0))*MIN(15/26*Census!$D12*(1+Assumptions!$B$9)^AU$5*(INT((Census!$F12+AU$5))+IF((Census!$F12+AU$5)-INT((Census!$F12+AU$5))>0.5,1,0)),Assumptions!$B$10)) -> 0
A13: =Census!A13 -> E008 | B13: =Census!H13 -> 25 | C13: =IF(C$5>$B13,0,INDEX(Decrements!$G$6:$G$58,Census!$G13+C$5-18)/INDEX(Decrements!$G$6:$G$58,Census!$G13-17)*(INDEX(Decrements!$D$6:$D$58,Census!$G13+C$5-18)+IF(C$5=$B13,INDEX(Decrements!$F$6:$F$58,Census!$G13+C$5-18),0)+INDEX(Decrements!$E$6:$E$58,Census!$G13+C$5-18)*IF((Census!$F13+C$5)>=Assumptions!$B$11,1,0))*MIN(15/26*Census!$D13*(1+Assumptions!$B$9)^C$5*(INT((Census!$F13+C$5))+IF((Census!$F13+C$5)-INT((Census!$F13+C$5))>0.5,1,0)),Assumptions!$B$10)) -> 25342.717 | D13: =IF(D$5>$B13,0,INDEX(Decrements!$G$6:$G$58,Census!$G13+D$5-18)/INDEX(Decrements!$G$6:$G$58,Census!$G13-17)*(INDEX(Decrements!$D$6:$D$58,Census!$G13+D$5-18)+IF(D$5=$B13,INDEX(Decrements!$F$6:$F$58,Census!$G13+D$5-18),0)+INDEX(Decrements!$E$6:$E$58,Census!$G13+D$5-18)*IF((Census!$F13+D$5)>=Assumptions!$B$11,1,0))*MIN(15/26*Census!$D13*(1+Assumptions!$B$9)^D$5*(INT((Census!$F13+D$5))+IF((Census!$F13+D$5)-INT((Census!$F13+D$5))>0.5,1,0)),Assumptions!$B$10)) -> 27460.871 | E13: =IF(E$5>$B13,0,INDEX(Decrements!$G$6:$G$58,Census!$G13+E$5-18)/INDEX(Decrements!$G$6:$G$58,Census!$G13-17)*(INDEX(Decrements!$D$6:$D$58,Census!$G13+E$5-18)+IF(E$5=$B13,INDEX(Decrements!$F$6:$F$58,Census!$G13+E$5-18),0)+INDEX(Decrements!$E$6:$E$58,Census!$G13+E$5-18)*IF((Census!$F13+E$5)>=Assumptions!$B$11,1,0))*MIN(15/26*Census!$D13*(1+Assumptions!$B$9)^E$5*(INT((Census!$F13+E$5))+IF((Census!$F13+E$5)-INT((Census!$F13+E$5))>0.5,1,0)),Assumptions!$B$10)) -> 29549.641 | F13: =IF(F$5>$B13,0,INDEX(Decrements!$G$6:$G$58,Census!$G13+F$5-18)/INDEX(Decrements!$G$6:$G$58,Census!$G13-17)*(INDEX(Decrements!$D$6:$D$58,Census!$G13+F$5-18)+IF(F$5=$B13,INDEX(Decrements!$F$6:$F$58,Census!$G13+F$5-18),0)+INDEX(Decrements!$E$6:$E$58,Census!$G13+F$5-18)*IF((Census!$F13+F$5)>=Assumptions!$B$11,1,0))*MIN(15/26*Census!$D13*(1+Assumptions!$B$9)^F$5*(INT((Census!$F13+F$5))+IF((Census!$F13+F$5)-INT((Census!$F13+F$5))>0.5,1,0)),Assumptions!$B$10)) -> 31609.396 | G13: =IF(G$5>$B13,0,INDEX(Decrements!$G$6:$G$58,Census!$G13+G$5-18)/INDEX(Decrements!$G$6:$G$58,Census!$G13-17)*(INDEX(Decrements!$D$6:$D$58,Census!$G13+G$5-18)+IF(G$5=$B13,INDEX(Decrements!$F$6:$F$58,Census!$G13+G$5-18),0)+INDEX(Decrements!$E$6:$E$58,Census!$G13+G$5-18)*IF((Census!$F13+G$5)>=Assumptions!$B$11,1,0))*MIN(15/26*Census!$D13*(1+Assumptions!$B$9)^G$5*(INT((Census!$F13+G$5))+IF((Census!$F13+G$5)-INT((Census!$F13+G$5))>0.5,1,0)),Assumptions!$B$10)) -> 33640.505 | H13: =IF(H$5>$B13,0,INDEX(Decrements!$G$6:$G$58,Census!$G13+H$5-18)/INDEX(Decrements!$G$6:$G$58,Census!$G13-17)*(INDEX(Decrements!$D$6:$D$58,Census!$G13+H$5-18)+IF(H$5=$B13,INDEX(Decrements!$F$6:$F$58,Census!$G13+H$5-18),0)+INDEX(Decrements!$E$6:$E$58,Census!$G13+H$5-18)*IF((Census!$F13+H$5)>=Assumptions!$B$11,1,0))*MIN(15/26*Census!$D13*(1+Assumptions!$B$9)^H$5*(INT((Census!$F13+H$5))+IF((Census!$F13+H$5)-INT((Census!$F13+H$5))>0.5,1,0)),Assumptions!$B$10)) -> 22499.003 | I13: =IF(I$5>$B13,0,INDEX(Decrements!$G$6:$G$58,Census!$G13+I$5-18)/INDEX(Decrements!$G$6:$G$58,Census!$G13-17)*(INDEX(Decrements!$D$6:$D$58,Census!$G13+I$5-18)+IF(I$5=$B13,INDEX(Decrements!$F$6:$F$58,Census!$G13+I$5-18),0)+INDEX(Decrements!$E$6:$E$58,Census!$G13+I$5-18)*IF((Census!$F13+I$5)>=Assumptions!$B$11,1,0))*MIN(15/26*Census!$D13*(1+Assumptions!$B$9)^I$5*(INT((Census!$F13+I$5))+IF((Census!$F13+I$5)-INT((Census!$F13+I$5))>0.5,1,0)),Assumptions!$B$10)) -> 24536.678 | J13: =IF(J$5>$B13,0,INDEX(Decrements!$G$6:$G$58,Census!$G13+J$5-18)/INDEX(Decrements!$G$6:$G$58,Census!$G13-17)*(INDEX(Decrements!$D$6:$D$58,Census!$G13+J$5-18)+IF(J$5=$B13,INDEX(Decrements!$F$6:$F$58,Census!$G13+J$5-18),0)+INDEX(Decrements!$E$6:$E$58,Census!$G13+J$5-18)*IF((Census!$F13+J$5)>=Assumptions!$B$11,1,0))*MIN(15/26*Census!$D13*(1+Assumptions!$B$9)^J$5*(INT((Census!$F13+J$5))+IF((Census!$F13+J$5)-INT((Census!$F13+J$5))>0.5,1,0)),Assumptions!$B$10)) -> 26668.356 | ... AU13: =IF(AU$5>$B13,0,INDEX(Decrements!$G$6:$G$58,Census!$G13+AU$5-18)/INDEX(Decrements!$G$6:$G$58,Census!$G13-17)*(INDEX(Decrements!$D$6:$D$58,Census!$G13+AU$5-18)+IF(AU$5=$B13,INDEX(Decrements!$F$6:$F$58,Census!$G13+AU$5-18),0)+INDEX(Decrements!$E$6:$E$58,Census!$G13+AU$5-18)*IF((Census!$F13+AU$5)>=Assumptions!$B$11,1,0))*MIN(15/26*Census!$D13*(1+Assumptions!$B$9)^AU$5*(INT((Census!$F13+AU$5))+IF((Census!$F13+AU$5)-INT((Census!$F13+AU$5))>0.5,1,0)),Assumptions!$B$10)) -> 0
A14: =Census!A14 -> E009 | B14: =Census!H14 -> 27 | C14: =IF(C$5>$B14,0,INDEX(Decrements!$G$6:$G$58,Census!$G14+C$5-18)/INDEX(Decrements!$G$6:$G$58,Census!$G14-17)*(INDEX(Decrements!$D$6:$D$58,Census!$G14+C$5-18)+IF(C$5=$B14,INDEX(Decrements!$F$6:$F$58,Census!$G14+C$5-18),0)+INDEX(Decrements!$E$6:$E$58,Census!$G14+C$5-18)*IF((Census!$F14+C$5)>=Assumptions!$B$11,1,0))*MIN(15/26*Census!$D14*(1+Assumptions!$B$9)^C$5*(INT((Census!$F14+C$5))+IF((Census!$F14+C$5)-INT((Census!$F14+C$5))>0.5,1,0)),Assumptions!$B$10)) -> 26.634866 | D14: =IF(D$5>$B14,0,INDEX(Decrements!$G$6:$G$58,Census!$G14+D$5-18)/INDEX(Decrements!$G$6:$G$58,Census!$G14-17)*(INDEX(Decrements!$D$6:$D$58,Census!$G14+D$5-18)+IF(D$5=$B14,INDEX(Decrements!$F$6:$F$58,Census!$G14+D$5-18),0)+INDEX(Decrements!$E$6:$E$58,Census!$G14+D$5-18)*IF((Census!$F14+D$5)>=Assumptions!$B$11,1,0))*MIN(15/26*Census!$D14*(1+Assumptions!$B$9)^D$5*(INT((Census!$F14+D$5))+IF((Census!$F14+D$5)-INT((Census!$F14+D$5))>0.5,1,0)),Assumptions!$B$10)) -> 40.474371 | E14: =IF(E$5>$B14,0,INDEX(Decrements!$G$6:$G$58,Census!$G14+E$5-18)/INDEX(Decrements!$G$6:$G$58,Census!$G14-17)*(INDEX(Decrements!$D$6:$D$58,Census!$G14+E$5-18)+IF(E$5=$B14,INDEX(Decrements!$F$6:$F$58,Census!$G14+E$5-18),0)+INDEX(Decrements!$E$6:$E$58,Census!$G14+E$5-18)*IF((Census!$F14+E$5)>=Assumptions!$B$11,1,0))*MIN(15/26*Census!$D14*(1+Assumptions!$B$9)^E$5*(INT((Census!$F14+E$5))+IF((Census!$F14+E$5)-INT((Census!$F14+E$5))>0.5,1,0)),Assumptions!$B$10)) -> 55.659523 | F14: =IF(F$5>$B14,0,INDEX(Decrements!$G$6:$G$58,Census!$G14+F$5-18)/INDEX(Decrements!$G$6:$G$58,Census!$G14-17)*(INDEX(Decrements!$D$6:$D$58,Census!$G14+F$5-18)+IF(F$5=$B14,INDEX(Decrements!$F$6:$F$58,Census!$G14+F$5-18),0)+INDEX(Decrements!$E$6:$E$58,Census!$G14+F$5-18)*IF((Census!$F14+F$5)>=Assumptions!$B$11,1,0))*MIN(15/26*Census!$D14*(1+Assumptions!$B$9)^F$5*(INT((Census!$F14+F$5))+IF((Census!$F14+F$5)-INT((Census!$F14+F$5))>0.5,1,0)),Assumptions!$B$10)) -> 73.173495 | G14: =IF(G$5>$B14,0,INDEX(Decrements!$G$6:$G$58,Census!$G14+G$5-18)/INDEX(Decrements!$G$6:$G$58,Census!$G14-17)*(INDEX(Decrements!$D$6:$D$58,Census!$G14+G$5-18)+IF(G$5=$B14,INDEX(Decrements!$F$6:$F$58,Census!$G14+G$5-18),0)+INDEX(Decrements!$E$6:$E$58,Census!$G14+G$5-18)*IF((Census!$F14+G$5)>=Assumptions!$B$11,1,0))*MIN(15/26*Census!$D14*(1+Assumptions!$B$9)^G$5*(INT((Census!$F14+G$5))+IF((Census!$F14+G$5)-INT((Census!$F14+G$5))>0.5,1,0)),Assumptions!$B$10)) -> 7018.1024 | H14: =IF(H$5>$B14,0,INDEX(Decrements!$G$6:$G$58,Census!$G14+H$5-18)/INDEX(Decrements!$G$6:$G$58,Census!$G14-17)*(INDEX(Decrements!$D$6:$D$58,Census!$G14+H$5-18)+IF(H$5=$B14,INDEX(Decrements!$F$6:$F$58,Census!$G14+H$5-18),0)+INDEX(Decrements!$E$6:$E$58,Census!$G14+H$5-18)*IF((Census!$F14+H$5)>=Assumptions!$B$11,1,0))*MIN(15/26*Census!$D14*(1+Assumptions!$B$9)^H$5*(INT((Census!$F14+H$5))+IF((Census!$F14+H$5)-INT((Census!$F14+H$5))>0.5,1,0)),Assumptions!$B$10)) -> 8132.9067 | I14: =IF(I$5>$B14,0,INDEX(Decrements!$G$6:$G$58,Census!$G14+I$5-18)/INDEX(Decrements!$G$6:$G$58,Census!$G14-17)*(INDEX(Decrements!$D$6:$D$58,Census!$G14+I$5-18)+IF(I$5=$B14,INDEX(Decrements!$F$6:$F$58,Census!$G14+I$5-18),0)+INDEX(Decrements!$E$6:$E$58,Census!$G14+I$5-18)*IF((Census!$F14+I$5)>=Assumptions!$B$11,1,0))*MIN(15/26*Census!$D14*(1+Assumptions!$B$9)^I$5*(INT((Census!$F14+I$5))+IF((Census!$F14+I$5)-INT((Census!$F14+I$5))>0.5,1,0)),Assumptions!$B$10)) -> 9232.532 | J14: =IF(J$5>$B14,0,INDEX(Decrements!$G$6:$G$58,Census!$G14+J$5-18)/INDEX(Decrements!$G$6:$G$58,Census!$G14-17)*(INDEX(Decrements!$D$6:$D$58,Census!$G14+J$5-18)+IF(J$5=$B14,INDEX(Decrements!$F$6:$F$58,Census!$G14+J$5-18),0)+INDEX(Decrements!$E$6:$E$58,Census!$G14+J$5-18)*IF((Census!$F14+J$5)>=Assumptions!$B$11,1,0))*MIN(15/26*Census!$D14*(1+Assumptions!$B$9)^J$5*(INT((Census!$F14+J$5))+IF((Census!$F14+J$5)-INT((Census!$F14+J$5))>0.5,1,0)),Assumptions!$B$10)) -> 6512.4649 | ... AU14: =IF(AU$5>$B14,0,INDEX(Decrements!$G$6:$G$58,Census!$G14+AU$5-18)/INDEX(Decrements!$G$6:$G$58,Census!$G14-17)*(INDEX(Decrements!$D$6:$D$58,Census!$G14+AU$5-18)+IF(AU$5=$B14,INDEX(Decrements!$F$6:$F$58,Census!$G14+AU$5-18),0)+INDEX(Decrements!$E$6:$E$58,Census!$G14+AU$5-18)*IF((Census!$F14+AU$5)>=Assumptions!$B$11,1,0))*MIN(15/26*Census!$D14*(1+Assumptions!$B$9)^AU$5*(INT((Census!$F14+AU$5))+IF((Census!$F14+AU$5)-INT((Census!$F14+AU$5))>0.5,1,0)),Assumptions!$B$10)) -> 0
A15: =Census!A15 -> E010 | B15: =Census!H15 -> 12 | C15: =IF(C$5>$B15,0,INDEX(Decrements!$G$6:$G$58,Census!$G15+C$5-18)/INDEX(Decrements!$G$6:$G$58,Census!$G15-17)*(INDEX(Decrements!$D$6:$D$58,Census!$G15+C$5-18)+IF(C$5=$B15,INDEX(Decrements!$F$6:$F$58,Census!$G15+C$5-18),0)+INDEX(Decrements!$E$6:$E$58,Census!$G15+C$5-18)*IF((Census!$F15+C$5)>=Assumptions!$B$11,1,0))*MIN(15/26*Census!$D15*(1+Assumptions!$B$9)^C$5*(INT((Census!$F15+C$5))+IF((Census!$F15+C$5)-INT((Census!$F15+C$5))>0.5,1,0)),Assumptions!$B$10)) -> 64719.742 | D15: =IF(D$5>$B15,0,INDEX(Decrements!$G$6:$G$58,Census!$G15+D$5-18)/INDEX(Decrements!$G$6:$G$58,Census!$G15-17)*(INDEX(Decrements!$D$6:$D$58,Census!$G15+D$5-18)+IF(D$5=$B15,INDEX(Decrements!$F$6:$F$58,Census!$G15+D$5-18),0)+INDEX(Decrements!$E$6:$E$58,Census!$G15+D$5-18)*IF((Census!$F15+D$5)>=Assumptions!$B$11,1,0))*MIN(15/26*Census!$D15*(1+Assumptions!$B$9)^D$5*(INT((Census!$F15+D$5))+IF((Census!$F15+D$5)-INT((Census!$F15+D$5))>0.5,1,0)),Assumptions!$B$10)) -> 63006.62 | E15: =IF(E$5>$B15,0,INDEX(Decrements!$G$6:$G$58,Census!$G15+E$5-18)/INDEX(Decrements!$G$6:$G$58,Census!$G15-17)*(INDEX(Decrements!$D$6:$D$58,Census!$G15+E$5-18)+IF(E$5=$B15,INDEX(Decrements!$F$6:$F$58,Census!$G15+E$5-18),0)+INDEX(Decrements!$E$6:$E$58,Census!$G15+E$5-18)*IF((Census!$F15+E$5)>=Assumptions!$B$11,1,0))*MIN(15/26*Census!$D15*(1+Assumptions!$B$9)^E$5*(INT((Census!$F15+E$5))+IF((Census!$F15+E$5)-INT((Census!$F15+E$5))>0.5,1,0)),Assumptions!$B$10)) -> 42691.701 | F15: =IF(F$5>$B15,0,INDEX(Decrements!$G$6:$G$58,Census!$G15+F$5-18)/INDEX(Decrements!$G$6:$G$58,Census!$G15-17)*(INDEX(Decrements!$D$6:$D$58,Census!$G15+F$5-18)+IF(F$5=$B15,INDEX(Decrements!$F$6:$F$58,Census!$G15+F$5-18),0)+INDEX(Decrements!$E$6:$E$58,Census!$G15+F$5-18)*IF((Census!$F15+F$5)>=Assumptions!$B$11,1,0))*MIN(15/26*Census!$D15*(1+Assumptions!$B$9)^F$5*(INT((Census!$F15+F$5))+IF((Census!$F15+F$5)-INT((Census!$F15+F$5))>0.5,1,0)),Assumptions!$B$10)) -> 42158.601 | G15: =IF(G$5>$B15,0,INDEX(Decrements!$G$6:$G$58,Census!$G15+G$5-18)/INDEX(Decrements!$G$6:$G$58,Census!$G15-17)*(INDEX(Decrements!$D$6:$D$58,Census!$G15+G$5-18)+IF(G$5=$B15,INDEX(Decrements!$F$6:$F$58,Census!$G15+G$5-18),0)+INDEX(Decrements!$E$6:$E$58,Census!$G15+G$5-18)*IF((Census!$F15+G$5)>=Assumptions!$B$11,1,0))*MIN(15/26*Census!$D15*(1+Assumptions!$B$9)^G$5*(INT((Census!$F15+G$5))+IF((Census!$F15+G$5)-INT((Census!$F15+G$5))>0.5,1,0)),Assumptions!$B$10)) -> 41660.26 | H15: =IF(H$5>$B15,0,INDEX(Decrements!$G$6:$G$58,Census!$G15+H$5-18)/INDEX(Decrements!$G$6:$G$58,Census!$G15-17)*(INDEX(Decrements!$D$6:$D$58,Census!$G15+H$5-18)+IF(H$5=$B15,INDEX(Decrements!$F$6:$F$58,Census!$G15+H$5-18),0)+INDEX(Decrements!$E$6:$E$58,Census!$G15+H$5-18)*IF((Census!$F15+H$5)>=Assumptions!$B$11,1,0))*MIN(15/26*Census!$D15*(1+Assumptions!$B$9)^H$5*(INT((Census!$F15+H$5))+IF((Census!$F15+H$5)-INT((Census!$F15+H$5))>0.5,1,0)),Assumptions!$B$10)) -> 41197.412 | I15: =IF(I$5>$B15,0,INDEX(Decrements!$G$6:$G$58,Census!$G15+I$5-18)/INDEX(Decrements!$G$6:$G$58,Census!$G15-17)*(INDEX(Decrements!$D$6:$D$58,Census!$G15+I$5-18)+IF(I$5=$B15,INDEX(Decrements!$F$6:$F$58,Census!$G15+I$5-18),0)+INDEX(Decrements!$E$6:$E$58,Census!$G15+I$5-18)*IF((Census!$F15+I$5)>=Assumptions!$B$11,1,0))*MIN(15/26*Census!$D15*(1+Assumptions!$B$9)^I$5*(INT((Census!$F15+I$5))+IF((Census!$F15+I$5)-INT((Census!$F15+I$5))>0.5,1,0)),Assumptions!$B$10)) -> 40770.814 | J15: =IF(J$5>$B15,0,INDEX(Decrements!$G$6:$G$58,Census!$G15+J$5-18)/INDEX(Decrements!$G$6:$G$58,Census!$G15-17)*(INDEX(Decrements!$D$6:$D$58,Census!$G15+J$5-18)+IF(J$5=$B15,INDEX(Decrements!$F$6:$F$58,Census!$G15+J$5-18),0)+INDEX(Decrements!$E$6:$E$58,Census!$G15+J$5-18)*IF((Census!$F15+J$5)>=Assumptions!$B$11,1,0))*MIN(15/26*Census!$D15*(1+Assumptions!$B$9)^J$5*(INT((Census!$F15+J$5))+IF((Census!$F15+J$5)-INT((Census!$F15+J$5))>0.5,1,0)),Assumptions!$B$10)) -> 23815.792 | ... AU15: =IF(AU$5>$B15,0,INDEX(Decrements!$G$6:$G$58,Census!$G15+AU$5-18)/INDEX(Decrements!$G$6:$G$58,Census!$G15-17)*(INDEX(Decrements!$D$6:$D$58,Census!$G15+AU$5-18)+IF(AU$5=$B15,INDEX(Decrements!$F$6:$F$58,Census!$G15+AU$5-18),0)+INDEX(Decrements!$E$6:$E$58,Census!$G15+AU$5-18)*IF((Census!$F15+AU$5)>=Assumptions!$B$11,1,0))*MIN(15/26*Census!$D15*(1+Assumptions!$B$9)^AU$5*(INT((Census!$F15+AU$5))+IF((Census!$F15+AU$5)-INT((Census!$F15+AU$5))>0.5,1,0)),Assumptions!$B$10)) -> 0
A16: =Census!A16 -> E011 | B16: =Census!H16 -> 29 | C16: =IF(C$5>$B16,0,INDEX(Decrements!$G$6:$G$58,Census!$G16+C$5-18)/INDEX(Decrements!$G$6:$G$58,Census!$G16-17)*(INDEX(Decrements!$D$6:$D$58,Census!$G16+C$5-18)+IF(C$5=$B16,INDEX(Decrements!$F$6:$F$58,Census!$G16+C$5-18),0)+INDEX(Decrements!$E$6:$E$58,Census!$G16+C$5-18)*IF((Census!$F16+C$5)>=Assumptions!$B$11,1,0))*MIN(15/26*Census!$D16*(1+Assumptions!$B$9)^C$5*(INT((Census!$F16+C$5))+IF((Census!$F16+C$5)-INT((Census!$F16+C$5))>0.5,1,0)),Assumptions!$B$10)) -> 61.801849 | D16: =IF(D$5>$B16,0,INDEX(Decrements!$G$6:$G$58,Census!$G16+D$5-18)/INDEX(Decrements!$G$6:$G$58,Census!$G16-17)*(INDEX(Decrements!$D$6:$D$58,Census!$G16+D$5-18)+IF(D$5=$B16,INDEX(Decrements!$F$6:$F$58,Census!$G16+D$5-18),0)+INDEX(Decrements!$E$6:$E$58,Census!$G16+D$5-18)*IF((Census!$F16+D$5)>=Assumptions!$B$11,1,0))*MIN(15/26*Census!$D16*(1+Assumptions!$B$9)^D$5*(INT((Census!$F16+D$5))+IF((Census!$F16+D$5)-INT((Census!$F16+D$5))>0.5,1,0)),Assumptions!$B$10)) -> 10835.982 | E16: =IF(E$5>$B16,0,INDEX(Decrements!$G$6:$G$58,Census!$G16+E$5-18)/INDEX(Decrements!$G$6:$G$58,Census!$G16-17)*(INDEX(Decrements!$D$6:$D$58,Census!$G16+E$5-18)+IF(E$5=$B16,INDEX(Decrements!$F$6:$F$58,Census!$G16+E$5-18),0)+INDEX(Decrements!$E$6:$E$58,Census!$G16+E$5-18)*IF((Census!$F16+E$5)>=Assumptions!$B$11,1,0))*MIN(15/26*Census!$D16*(1+Assumptions!$B$9)^E$5*(INT((Census!$F16+E$5))+IF((Census!$F16+E$5)-INT((Census!$F16+E$5))>0.5,1,0)),Assumptions!$B$10)) -> 12492.565 | F16: =IF(F$5>$B16,0,INDEX(Decrements!$G$6:$G$58,Census!$G16+F$5-18)/INDEX(Decrements!$G$6:$G$58,Census!$G16-17)*(INDEX(Decrements!$D$6:$D$58,Census!$G16+F$5-18)+IF(F$5=$B16,INDEX(Decrements!$F$6:$F$58,Census!$G16+F$5-18),0)+INDEX(Decrements!$E$6:$E$58,Census!$G16+F$5-18)*IF((Census!$F16+F$5)>=Assumptions!$B$11,1,0))*MIN(15/26*Census!$D16*(1+Assumptions!$B$9)^F$5*(INT((Census!$F16+F$5))+IF((Census!$F16+F$5)-INT((Census!$F16+F$5))>0.5,1,0)),Assumptions!$B$10)) -> 14002.212 | G16: =IF(G$5>$B16,0,INDEX(Decrements!$G$6:$G$58,Census!$G16+G$5-18)/INDEX(Decrements!$G$6:$G$58,Census!$G16-17)*(INDEX(Decrements!$D$6:$D$58,Census!$G16+G$5-18)+IF(G$5=$B16,INDEX(Decrements!$F$6:$F$58,Census!$G16+G$5-18),0)+INDEX(Decrements!$E$6:$E$58,Census!$G16+G$5-18)*IF((Census!$F16+G$5)>=Assumptions!$B$11,1,0))*MIN(15/26*Census!$D16*(1+Assumptions!$B$9)^G$5*(INT((Census!$F16+G$5))+IF((Census!$F16+G$5)-INT((Census!$F16+G$5))>0.5,1,0)),Assumptions!$B$10)) -> 11218.386 | H16: =IF(H$5>$B16,0,INDEX(Decrements!$G$6:$G$58,Census!$G16+H$5-18)/INDEX(Decrements!$G$6:$G$58,Census!$G16-17)*(INDEX(Decrements!$D$6:$D$58,Census!$G16+H$5-18)+IF(H$5=$B16,INDEX(Decrements!$F$6:$F$58,Census!$G16+H$5-18),0)+INDEX(Decrements!$E$6:$E$58,Census!$G16+H$5-18)*IF((Census!$F16+H$5)>=Assumptions!$B$11,1,0))*MIN(15/26*Census!$D16*(1+Assumptions!$B$9)^H$5*(INT((Census!$F16+H$5))+IF((Census!$F16+H$5)-INT((Census!$F16+H$5))>0.5,1,0)),Assumptions!$B$10)) -> 12535.899 | I16: =IF(I$5>$B16,0,INDEX(Decrements!$G$6:$G$58,Census!$G16+I$5-18)/INDEX(Decrements!$G$6:$G$58,Census!$G16-17)*(INDEX(Decrements!$D$6:$D$58,Census!$G16+I$5-18)+IF(I$5=$B16,INDEX(Decrements!$F$6:$F$58,Census!$G16+I$5-18),0)+INDEX(Decrements!$E$6:$E$58,Census!$G16+I$5-18)*IF((Census!$F16+I$5)>=Assumptions!$B$11,1,0))*MIN(15/26*Census!$D16*(1+Assumptions!$B$9)^I$5*(INT((Census!$F16+I$5))+IF((Census!$F16+I$5)-INT((Census!$F16+I$5))>0.5,1,0)),Assumptions!$B$10)) -> 13835.306 | J16: =IF(J$5>$B16,0,INDEX(Decrements!$G$6:$G$58,Census!$G16+J$5-18)/INDEX(Decrements!$G$6:$G$58,Census!$G16-17)*(INDEX(Decrements!$D$6:$D$58,Census!$G16+J$5-18)+IF(J$5=$B16,INDEX(Decrements!$F$6:$F$58,Census!$G16+J$5-18),0)+INDEX(Decrements!$E$6:$E$58,Census!$G16+J$5-18)*IF((Census!$F16+J$5)>=Assumptions!$B$11,1,0))*MIN(15/26*Census!$D16*(1+Assumptions!$B$9)^J$5*(INT((Census!$F16+J$5))+IF((Census!$F16+J$5)-INT((Census!$F16+J$5))>0.5,1,0)),Assumptions!$B$10)) -> 15116.831 | ... AU16: =IF(AU$5>$B16,0,INDEX(Decrements!$G$6:$G$58,Census!$G16+AU$5-18)/INDEX(Decrements!$G$6:$G$58,Census!$G16-17)*(INDEX(Decrements!$D$6:$D$58,Census!$G16+AU$5-18)+IF(AU$5=$B16,INDEX(Decrements!$F$6:$F$58,Census!$G16+AU$5-18),0)+INDEX(Decrements!$E$6:$E$58,Census!$G16+AU$5-18)*IF((Census!$F16+AU$5)>=Assumptions!$B$11,1,0))*MIN(15/26*Census!$D16*(1+Assumptions!$B$9)^AU$5*(INT((Census!$F16+AU$5))+IF((Census!$F16+AU$5)-INT((Census!$F16+AU$5))>0.5,1,0)),Assumptions!$B$10)) -> 0
A17: =Census!A17 -> E012 | B17: =Census!H17 -> 22 | C17: =IF(C$5>$B17,0,INDEX(Decrements!$G$6:$G$58,Census!$G17+C$5-18)/INDEX(Decrements!$G$6:$G$58,Census!$G17-17)*(INDEX(Decrements!$D$6:$D$58,Census!$G17+C$5-18)+IF(C$5=$B17,INDEX(Decrements!$F$6:$F$58,Census!$G17+C$5-18),0)+INDEX(Decrements!$E$6:$E$58,Census!$G17+C$5-18)*IF((Census!$F17+C$5)>=Assumptions!$B$11,1,0))*MIN(15/26*Census!$D17*(1+Assumptions!$B$9)^C$5*(INT((Census!$F17+C$5))+IF((Census!$F17+C$5)-INT((Census!$F17+C$5))>0.5,1,0)),Assumptions!$B$10)) -> 105420.35 | D17: =IF(D$5>$B17,0,INDEX(Decrements!$G$6:$G$58,Census!$G17+D$5-18)/INDEX(Decrements!$G$6:$G$58,Census!$G17-17)*(INDEX(Decrements!$D$6:$D$58,Census!$G17+D$5-18)+IF(D$5=$B17,INDEX(Decrements!$F$6:$F$58,Census!$G17+D$5-18),0)+INDEX(Decrements!$E$6:$E$58,Census!$G17+D$5-18)*IF((Census!$F17+D$5)>=Assumptions!$B$11,1,0))*MIN(15/26*Census!$D17*(1+Assumptions!$B$9)^D$5*(INT((Census!$F17+D$5))+IF((Census!$F17+D$5)-INT((Census!$F17+D$5))>0.5,1,0)),Assumptions!$B$10)) -> 111695.65 | E17: =IF(E$5>$B17,0,INDEX(Decrements!$G$6:$G$58,Census!$G17+E$5-18)/INDEX(Decrements!$G$6:$G$58,Census!$G17-17)*(INDEX(Decrements!$D$6:$D$58,Census!$G17+E$5-18)+IF(E$5=$B17,INDEX(Decrements!$F$6:$F$58,Census!$G17+E$5-18),0)+INDEX(Decrements!$E$6:$E$58,Census!$G17+E$5-18)*IF((Census!$F17+E$5)>=Assumptions!$B$11,1,0))*MIN(15/26*Census!$D17*(1+Assumptions!$B$9)^E$5*(INT((Census!$F17+E$5))+IF((Census!$F17+E$5)-INT((Census!$F17+E$5))>0.5,1,0)),Assumptions!$B$10)) -> 74411.021 | F17: =IF(F$5>$B17,0,INDEX(Decrements!$G$6:$G$58,Census!$G17+F$5-18)/INDEX(Decrements!$G$6:$G$58,Census!$G17-17)*(INDEX(Decrements!$D$6:$D$58,Census!$G17+F$5-18)+IF(F$5=$B17,INDEX(Decrements!$F$6:$F$58,Census!$G17+F$5-18),0)+INDEX(Decrements!$E$6:$E$58,Census!$G17+F$5-18)*IF((Census!$F17+F$5)>=Assumptions!$B$11,1,0))*MIN(15/26*Census!$D17*(1+Assumptions!$B$9)^F$5*(INT((Census!$F17+F$5))+IF((Census!$F17+F$5)-INT((Census!$F17+F$5))>0.5,1,0)),Assumptions!$B$10)) -> 80869.431 | G17: =IF(G$5>$B17,0,INDEX(Decrements!$G$6:$G$58,Census!$G17+G$5-18)/INDEX(Decrements!$G$6:$G$58,Census!$G17-17)*(INDEX(Decrements!$D$6:$D$58,Census!$G17+G$5-18)+IF(G$5=$B17,INDEX(Decrements!$F$6:$F$58,Census!$G17+G$5-18),0)+INDEX(Decrements!$E$6:$E$58,Census!$G17+G$5-18)*IF((Census!$F17+G$5)>=Assumptions!$B$11,1,0))*MIN(15/26*Census!$D17*(1+Assumptions!$B$9)^G$5*(INT((Census!$F17+G$5))+IF((Census!$F17+G$5)-INT((Census!$F17+G$5))>0.5,1,0)),Assumptions!$B$10)) -> 78223.089 | H17: =IF(H$5>$B17,0,INDEX(Decrements!$G$6:$G$58,Census!$G17+H$5-18)/INDEX(Decrements!$G$6:$G$58,Census!$G17-17)*(INDEX(Decrements!$D$6:$D$58,Census!$G17+H$5-18)+IF(H$5=$B17,INDEX(Decrements!$F$6:$F$58,Census!$G17+H$5-18),0)+INDEX(Decrements!$E$6:$E$58,Census!$G17+H$5-18)*IF((Census!$F17+H$5)>=Assumptions!$B$11,1,0))*MIN(15/26*Census!$D17*(1+Assumptions!$B$9)^H$5*(INT((Census!$F17+H$5))+IF((Census!$F17+H$5)-INT((Census!$F17+H$5))>0.5,1,0)),Assumptions!$B$10)) -> 74354.023 | I17: =IF(I$5>$B17,0,INDEX(Decrements!$G$6:$G$58,Census!$G17+I$5-18)/INDEX(Decrements!$G$6:$G$58,Census!$G17-17)*(INDEX(Decrements!$D$6:$D$58,Census!$G17+I$5-18)+IF(I$5=$B17,INDEX(Decrements!$F$6:$F$58,Census!$G17+I$5-18),0)+INDEX(Decrements!$E$6:$E$58,Census!$G17+I$5-18)*IF((Census!$F17+I$5)>=Assumptions!$B$11,1,0))*MIN(15/26*Census!$D17*(1+Assumptions!$B$9)^I$5*(INT((Census!$F17+I$5))+IF((Census!$F17+I$5)-INT((Census!$F17+I$5))>0.5,1,0)),Assumptions!$B$10)) -> 70682.775 | J17: =IF(J$5>$B17,0,INDEX(Decrements!$G$6:$G$58,Census!$G17+J$5-18)/INDEX(Decrements!$G$6:$G$58,Census!$G17-17)*(INDEX(Decrements!$D$6:$D$58,Census!$G17+J$5-18)+IF(J$5=$B17,INDEX(Decrements!$F$6:$F$58,Census!$G17+J$5-18),0)+INDEX(Decrements!$E$6:$E$58,Census!$G17+J$5-18)*IF((Census!$F17+J$5)>=Assumptions!$B$11,1,0))*MIN(15/26*Census!$D17*(1+Assumptions!$B$9)^J$5*(INT((Census!$F17+J$5))+IF((Census!$F17+J$5)-INT((Census!$F17+J$5))>0.5,1,0)),Assumptions!$B$10)) -> 41319.375 | ... AU17: =IF(AU$5>$B17,0,INDEX(Decrements!$G$6:$G$58,Census!$G17+AU$5-18)/INDEX(Decrements!$G$6:$G$58,Census!$G17-17)*(INDEX(Decrements!$D$6:$D$58,Census!$G17+AU$5-18)+IF(AU$5=$B17,INDEX(Decrements!$F$6:$F$58,Census!$G17+AU$5-18),0)+INDEX(Decrements!$E$6:$E$58,Census!$G17+AU$5-18)*IF((Census!$F17+AU$5)>=Assumptions!$B$11,1,0))*MIN(15/26*Census!$D17*(1+Assumptions!$B$9)^AU$5*(INT((Census!$F17+AU$5))+IF((Census!$F17+AU$5)-INT((Census!$F17+AU$5))>0.5,1,0)),Assumptions!$B$10)) -> 0
... A155: =Census!A155 -> E150 | B155: =Census!H155 -> 16 | C155: =IF(C$5>$B155,0,INDEX(Decrements!$G$6:$G$58,Census!$G155+C$5-18)/INDEX(Decrements!$G$6:$G$58,Census!$G155-17)*(INDEX(Decrements!$D$6:$D$58,Census!$G155+C$5-18)+IF(C$5=$B155,INDEX(Decrements!$F$6:$F$58,Census!$G155+C$5-18),0)+INDEX(Decrements!$E$6:$E$58,Census!$G155+C$5-18)*IF((Census!$F155+C$5)>=Assumptions!$B$11,1,0))*MIN(15/26*Census!$D155*(1+Assumptions!$B$9)^C$5*(INT((Census!$F155+C$5))+IF((Census!$F155+C$5)-INT((Census!$F155+C$5))>0.5,1,0)),Assumptions!$B$10)) -> 34686.67 | D155: =IF(D$5>$B155,0,INDEX(Decrements!$G$6:$G$58,Census!$G155+D$5-18)/INDEX(Decrements!$G$6:$G$58,Census!$G155-17)*(INDEX(Decrements!$D$6:$D$58,Census!$G155+D$5-18)+IF(D$5=$B155,INDEX(Decrements!$F$6:$F$58,Census!$G155+D$5-18),0)+INDEX(Decrements!$E$6:$E$58,Census!$G155+D$5-18)*IF((Census!$F155+D$5)>=Assumptions!$B$11,1,0))*MIN(15/26*Census!$D155*(1+Assumptions!$B$9)^D$5*(INT((Census!$F155+D$5))+IF((Census!$F155+D$5)-INT((Census!$F155+D$5))>0.5,1,0)),Assumptions!$B$10)) -> 23267.807 | E155: =IF(E$5>$B155,0,INDEX(Decrements!$G$6:$G$58,Census!$G155+E$5-18)/INDEX(Decrements!$G$6:$G$58,Census!$G155-17)*(INDEX(Decrements!$D$6:$D$58,Census!$G155+E$5-18)+IF(E$5=$B155,INDEX(Decrements!$F$6:$F$58,Census!$G155+E$5-18),0)+INDEX(Decrements!$E$6:$E$58,Census!$G155+E$5-18)*IF((Census!$F155+E$5)>=Assumptions!$B$11,1,0))*MIN(15/26*Census!$D155*(1+Assumptions!$B$9)^E$5*(INT((Census!$F155+E$5))+IF((Census!$F155+E$5)-INT((Census!$F155+E$5))>0.5,1,0)),Assumptions!$B$10)) -> 25879.126 | F155: =IF(F$5>$B155,0,INDEX(Decrements!$G$6:$G$58,Census!$G155+F$5-18)/INDEX(Decrements!$G$6:$G$58,Census!$G155-17)*(INDEX(Decrements!$D$6:$D$58,Census!$G155+F$5-18)+IF(F$5=$B155,INDEX(Decrements!$F$6:$F$58,Census!$G155+F$5-18),0)+INDEX(Decrements!$E$6:$E$58,Census!$G155+F$5-18)*IF((Census!$F155+F$5)>=Assumptions!$B$11,1,0))*MIN(15/26*Census!$D155*(1+Assumptions!$B$9)^F$5*(INT((Census!$F155+F$5))+IF((Census!$F155+F$5)-INT((Census!$F155+F$5))>0.5,1,0)),Assumptions!$B$10)) -> 28702.854 | G155: =IF(G$5>$B155,0,INDEX(Decrements!$G$6:$G$58,Census!$G155+G$5-18)/INDEX(Decrements!$G$6:$G$58,Census!$G155-17)*(INDEX(Decrements!$D$6:$D$58,Census!$G155+G$5-18)+IF(G$5=$B155,INDEX(Decrements!$F$6:$F$58,Census!$G155+G$5-18),0)+INDEX(Decrements!$E$6:$E$58,Census!$G155+G$5-18)*IF((Census!$F155+G$5)>=Assumptions!$B$11,1,0))*MIN(15/26*Census!$D155*(1+Assumptions!$B$9)^G$5*(INT((Census!$F155+G$5))+IF((Census!$F155+G$5)-INT((Census!$F155+G$5))>0.5,1,0)),Assumptions!$B$10)) -> 31756.296 | H155: =IF(H$5>$B155,0,INDEX(Decrements!$G$6:$G$58,Census!$G155+H$5-18)/INDEX(Decrements!$G$6:$G$58,Census!$G155-17)*(INDEX(Decrements!$D$6:$D$58,Census!$G155+H$5-18)+IF(H$5=$B155,INDEX(Decrements!$F$6:$F$58,Census!$G155+H$5-18),0)+INDEX(Decrements!$E$6:$E$58,Census!$G155+H$5-18)*IF((Census!$F155+H$5)>=Assumptions!$B$11,1,0))*MIN(15/26*Census!$D155*(1+Assumptions!$B$9)^H$5*(INT((Census!$F155+H$5))+IF((Census!$F155+H$5)-INT((Census!$F155+H$5))>0.5,1,0)),Assumptions!$B$10)) -> 35058.417 | I155: =IF(I$5>$B155,0,INDEX(Decrements!$G$6:$G$58,Census!$G155+I$5-18)/INDEX(Decrements!$G$6:$G$58,Census!$G155-17)*(INDEX(Decrements!$D$6:$D$58,Census!$G155+I$5-18)+IF(I$5=$B155,INDEX(Decrements!$F$6:$F$58,Census!$G155+I$5-18),0)+INDEX(Decrements!$E$6:$E$58,Census!$G155+I$5-18)*IF((Census!$F155+I$5)>=Assumptions!$B$11,1,0))*MIN(15/26*Census!$D155*(1+Assumptions!$B$9)^I$5*(INT((Census!$F155+I$5))+IF((Census!$F155+I$5)-INT((Census!$F155+I$5))>0.5,1,0)),Assumptions!$B$10)) -> 26876.748 | J155: =IF(J$5>$B155,0,INDEX(Decrements!$G$6:$G$58,Census!$G155+J$5-18)/INDEX(Decrements!$G$6:$G$58,Census!$G155-17)*(INDEX(Decrements!$D$6:$D$58,Census!$G155+J$5-18)+IF(J$5=$B155,INDEX(Decrements!$F$6:$F$58,Census!$G155+J$5-18),0)+INDEX(Decrements!$E$6:$E$58,Census!$G155+J$5-18)*IF((Census!$F155+J$5)>=Assumptions!$B$11,1,0))*MIN(15/26*Census!$D155*(1+Assumptions!$B$9)^J$5*(INT((Census!$F155+J$5))+IF((Census!$F155+J$5)-INT((Census!$F155+J$5))>0.5,1,0)),Assumptions!$B$10)) -> 29967.351 | ... AU155: =IF(AU$5>$B155,0,INDEX(Decrements!$G$6:$G$58,Census!$G155+AU$5-18)/INDEX(Decrements!$G$6:$G$58,Census!$G155-17)*(INDEX(Decrements!$D$6:$D$58,Census!$G155+AU$5-18)+IF(AU$5=$B155,INDEX(Decrements!$F$6:$F$58,Census!$G155+AU$5-18),0)+INDEX(Decrements!$E$6:$E$58,Census!$G155+AU$5-18)*IF((Census!$F155+AU$5)>=Assumptions!$B$11,1,0))*MIN(15/26*Census!$D155*(1+Assumptions!$B$9)^AU$5*(INT((Census!$F155+AU$5))+IF((Census!$F155+AU$5)-INT((Census!$F155+AU$5))>0.5,1,0)),Assumptions!$B$10)) -> 0

Sheet Employee_Workings
A1: One employee, line by line
A2: Type any employee ID in B3. This sheet shows the full working behind that person's DBO.
A3: Employee ID | B3: E003 | D3: DBO (Rs) | E3: =SUM(O16:O60) -> 445115.16
A4: Row in Census | B4: =MATCH(B3,Census!$A$6:$A$155,0) -> 3 | D4: Current service cost (Rs) | E4: =SUM(P16:P60) -> 32022.516
A5: Age at valuation | B5: =INDEX(Census!$E$6:$E$155,$B$4) -> 39.969884 | D5: DBO on Census sheet (Rs) | E5: =INDEX(Census!$L$6:$L$155,$B$4) -> 445115.16
A6: Service at valuation (years) | B6: =INDEX(Census!$F$6:$F$155,$B$4) -> 13.900068 | D6: Difference (should be 0) | E6: =E3-E5 -> 0
A7: Start age (rounded down) | B7: =INDEX(Census!$G$6:$G$155,$B$4) -> 39
A8: Years to retirement | B8: =INDEX(Census!$H$6:$H$155,$B$4) -> 21
A9: Monthly wages (Rs) | B9: =INDEX(Census!$D$6:$D$155,$B$4) -> 99400
A15: t (years from valuation) | B15: Age at start of year | C15: In service at start | D15: P(death in year) | E15: P(withdraw in year) | F15: P(retire at end) | G15: Service at exit (years) | H15: Projected monthly wages at exit (Rs) | I15: Years for formula | J15: Benefit if paid (Rs) | K15: P(paid) | L15: Expected benefit (Rs) | M15: Share earned to date | N15: Discount factor | O15: PV attributed (Rs) | P15: PV service cost part (Rs)
A16: 1 | B16: =IF($A16>$B$8,"",$B$7+$A16-1) -> 39 | C16: =IF($A16>$B$8,"",INDEX(Decrements!$G$6:$G$58,$B$7+$A16-18)/INDEX(Decrements!$G$6:$G$58,$B$7-17)) -> 1 | D16: =IF($A16>$B$8,"",C16*INDEX(Decrements!$D$6:$D$58,$B$7+$A16-18)) -> 0.0012120855 | E16: =IF($A16>$B$8,"",C16*INDEX(Decrements!$E$6:$E$58,$B$7+$A16-18)) -> 0.079949496 | F16: =IF($A16>$B$8,"",IF($A16=$B$8,C16*INDEX(Decrements!$F$6:$F$58,$B$7+$A16-18),0)) -> 0 | G16: =IF($A16>$B$8,"",$B$6+$A16) -> 14.900068 | H16: =IF($A16>$B$8,"",$B$9*(1+Assumptions!$B$9)^$A16) -> 107352 | I16: =IF($A16>$B$8,"",INT(G16)+IF(G16-INT(G16)>0.5,1,0)) -> 15 | J16: =IF($A16>$B$8,"",MIN(15/26*H16*I16,Assumptions!$B$10)) -> 929007.69 | K16: =IF($A16>$B$8,"",D16+F16+E16*IF(G16>=Assumptions!$B$11,1,0)) -> 0.081161582 | L16: =IF($A16>$B$8,"",K16*J16) -> 75399.734 | M16: =IF($A16>$B$8,"",$B$6/G16) -> 0.93288621 | N16: =IF($A16>$B$8,"",(1/(1+Assumptions!$B$8))^$A16) -> 0.93457944 | O16: =IF($A16>$B$8,"",L16*M16*N16) -> 65737.731 | P16: =IF($A16>$B$8,"",L16/G16*N16) -> 4729.3099
A17: =A16+1 -> 2 | B17: =IF($A17>$B$8,"",$B$7+$A17-1) -> 40 | C17: =IF($A17>$B$8,"",INDEX(Decrements!$G$6:$G$58,$B$7+$A17-18)/INDEX(Decrements!$G$6:$G$58,$B$7-17)) -> 0.91883842 | D17: =IF($A17>$B$8,"",C17*INDEX(Decrements!$D$6:$D$58,$B$7+$A17-18)) -> 0.0012083595 | E17: =IF($A17>$B$8,"",C17*INDEX(Decrements!$E$6:$E$58,$B$7+$A17-18)) -> 0.045910937 | F17: =IF($A17>$B$8,"",IF($A17=$B$8,C17*INDEX(Decrements!$F$6:$F$58,$B$7+$A17-18),0)) -> 0 | G17: =IF($A17>$B$8,"",$B$6+$A17) -> 15.900068 | H17: =IF($A17>$B$8,"",$B$9*(1+Assumptions!$B$9)^$A17) -> 115940.16 | I17: =IF($A17>$B$8,"",INT(G17)+IF(G17-INT(G17)>0.5,1,0)) -> 16 | J17: =IF($A17>$B$8,"",MIN(15/26*H17*I17,Assumptions!$B$10)) -> 1070216.9 | K17: =IF($A17>$B$8,"",D17+F17+E17*IF(G17>=Assumptions!$B$11,1,0)) -> 0.047119297 | L17: =IF($A17>$B$8,"",K17*J17) -> 50427.866 | M17: =IF($A17>$B$8,"",$B$6/G17) -> 0.87421438 | N17: =IF($A17>$B$8,"",(1/(1+Assumptions!$B$8))^$A17) -> 0.87343873 | O17: =IF($A17>$B$8,"",L17*M17*N17) -> 38505.342 | P17: =IF($A17>$B$8,"",L17/G17*N17) -> 2770.1548
A18: =A17+1 -> 3 | B18: =IF($A18>$B$8,"",$B$7+$A18-1) -> 41 | C18: =IF($A18>$B$8,"",INDEX(Decrements!$G$6:$G$58,$B$7+$A18-18)/INDEX(Decrements!$G$6:$G$58,$B$7-17)) -> 0.87171912 | D18: =IF($A18>$B$8,"",C18*INDEX(Decrements!$D$6:$D$58,$B$7+$A18-18)) -> 0.0012270001 | E18: =IF($A18>$B$8,"",C18*INDEX(Decrements!$E$6:$E$58,$B$7+$A18-18)) -> 0.043554495 | F18: =IF($A18>$B$8,"",IF($A18=$B$8,C18*INDEX(Decrements!$F$6:$F$58,$B$7+$A18-18),0)) -> 0 | G18: =IF($A18>$B$8,"",$B$6+$A18) -> 16.900068 | H18: =IF($A18>$B$8,"",$B$9*(1+Assumptions!$B$9)^$A18) -> 125215.37 | I18: =IF($A18>$B$8,"",INT(G18)+IF(G18-INT(G18)>0.5,1,0)) -> 17 | J18: =IF($A18>$B$8,"",MIN(15/26*H18*I18,Assumptions!$B$10)) -> 1228073.8 | K18: =IF($A18>$B$8,"",D18+F18+E18*IF(G18>=Assumptions!$B$11,1,0)) -> 0.044781495 | L18: =IF($A18>$B$8,"",K18*J18) -> 54994.982 | M18: =IF($A18>$B$8,"",$B$6/G18) -> 0.82248593 | N18: =IF($A18>$B$8,"",(1/(1+Assumptions!$B$8))^$A18) -> 0.81629788 | O18: =IF($A18>$B$8,"",L18*M18*N18) -> 36923.275 | P18: =IF($A18>$B$8,"",L18/G18*N18) -> 2656.3376
A19: =A18+1 -> 4 | B19: =IF($A19>$B$8,"",$B$7+$A19-1) -> 42 | C19: =IF($A19>$B$8,"",INDEX(Decrements!$G$6:$G$58,$B$7+$A19-18)/INDEX(Decrements!$G$6:$G$58,$B$7-17)) -> 0.82693763 | D19: =IF($A19>$B$8,"",C19*INDEX(Decrements!$D$6:$D$58,$B$7+$A19-18)) -> 0.0012480716 | E19: =IF($A19>$B$8,"",C19*INDEX(Decrements!$E$6:$E$58,$B$7+$A19-18)) -> 0.041314879 | F19: =IF($A19>$B$8,"",IF($A19=$B$8,C19*INDEX(Decrements!$F$6:$F$58,$B$7+$A19-18),0)) -> 0 | G19: =IF($A19>$B$8,"",$B$6+$A19) -> 17.900068 | H19: =IF($A19>$B$8,"",$B$9*(1+Assumptions!$B$9)^$A19) -> 135232.6 | I19: =IF($A19>$B$8,"",INT(G19)+IF(G19-INT(G19)>0.5,1,0)) -> 18 | J19: =IF($A19>$B$8,"",MIN(15/26*H19*I19,Assumptions!$B$10)) -> 1404338.6 | K19: =IF($A19>$B$8,"",D19+F19+E19*IF(G19>=Assumptions!$B$11,1,0)) -> 0.042562951 | L19: =IF($A19>$B$8,"",K19*J19) -> 59772.794 | M19: =IF($A19>$B$8,"",$B$6/G19) -> 0.77653717 | N19: =IF($A19>$B$8,"",(1/(1+Assumptions!$B$8))^$A19) -> 0.76289521 | O19: =IF($A19>$B$8,"",L19*M19*N19) -> 35410.388 | P19: =IF($A19>$B$8,"",L19/G19*N19) -> 2547.4974
A20: =A19+1 -> 5 | B20: =IF($A20>$B$8,"",$B$7+$A20-1) -> 43 | C20: =IF($A20>$B$8,"",INDEX(Decrements!$G$6:$G$58,$B$7+$A20-18)/INDEX(Decrements!$G$6:$G$58,$B$7-17)) -> 0.78437468 | D20: =IF($A20>$B$8,"",C20*INDEX(Decrements!$D$6:$D$58,$B$7+$A20-18)) -> 0.0012715759 | E20: =IF($A20>$B$8,"",C20*INDEX(Decrements!$E$6:$E$58,$B$7+$A20-18)) -> 0.039186129 | F20: =IF($A20>$B$8,"",IF($A20=$B$8,C20*INDEX(Decrements!$F$6:$F$58,$B$7+$A20-18),0)) -> 0 | G20: =IF($A20>$B$8,"",$B$6+$A20) -> 18.900068 | H20: =IF($A20>$B$8,"",$B$9*(1+Assumptions!$B$9)^$A20) -> 146051.21 | I20: =IF($A20>$B$8,"",INT(G20)+IF(G20-INT(G20)>0.5,1,0)) -> 19 | J20: =IF($A20>$B$8,"",MIN(15/26*H20*I20,Assumptions!$B$10)) -> 1600946 | K20: =IF($A20>$B$8,"",D20+F20+E20*IF(G20>=Assumptions!$B$11,1,0)) -> 0.040457705 | L20: =IF($A20>$B$8,"",K20*J20) -> 64770.6 | M20: =IF($A20>$B$8,"",$B$6/G20) -> 0.73545069 | N20: =IF($A20>$B$8,"",(1/(1+Assumptions!$B$8))^$A20) -> 0.71298618 | O20: =IF($A20>$B$8,"",L20*M20*N20) -> 33963.512 | P20: =IF($A20>$B$8,"",L20/G20*N20) -> 2443.4061
A21: =A20+1 -> 6 | B21: =IF($A21>$B$8,"",$B$7+$A21-1) -> 44 | C21: =IF($A21>$B$8,"",INDEX(Decrements!$G$6:$G$58,$B$7+$A21-18)/INDEX(Decrements!$G$6:$G$58,$B$7-17)) -> 0.74391697 | D21: =IF($A21>$B$8,"",C21*INDEX(Decrements!$D$6:$D$58,$B$7+$A21-18)) -> 0.0012975168 | E21: =IF($A21>$B$8,"",C21*INDEX(Decrements!$E$6:$E$58,$B$7+$A21-18)) -> 0.037162579 | F21: =IF($A21>$B$8,"",IF($A21=$B$8,C21*INDEX(Decrements!$F$6:$F$58,$B$7+$A21-18),0)) -> 0 | G21: =IF($A21>$B$8,"",$B$6+$A21) -> 19.900068 | H21: =IF($A21>$B$8,"",$B$9*(1+Assumptions!$B$9)^$A21) -> 157735.31 | I21: =IF($A21>$B$8,"",INT(G21)+IF(G21-INT(G21)>0.5,1,0)) -> 20 | J21: =IF($A21>$B$8,"",MIN(15/26*H21*I21,Assumptions!$B$10)) -> 1820022.8 | K21: =IF($A21>$B$8,"",D21+F21+E21*IF(G21>=Assumptions!$B$11,1,0)) -> 0.038460096 | L21: =IF($A21>$B$8,"",K21*J21) -> 69998.25 | M21: =IF($A21>$B$8,"",$B$6/G21) -> 0.6984935 | N21: =IF($A21>$B$8,"",(1/(1+Assumptions!$B$8))^$A21) -> 0.66634222 | O21: =IF($A21>$B$8,"",L21*M21*N21) -> 32579.685 | P21: =IF($A21>$B$8,"",L21/G21*N21) -> 2343.8507
A22: =A21+1 -> 7 | B22: =IF($A22>$B$8,"",$B$7+$A22-1) -> 45 | C22: =IF($A22>$B$8,"",INDEX(Decrements!$G$6:$G$58,$B$7+$A22-18)/INDEX(Decrements!$G$6:$G$58,$B$7-17)) -> 0.70545687 | D22: =IF($A22>$B$8,"",C22*INDEX(Decrements!$D$6:$D$58,$B$7+$A22-18)) -> 0.0013394981 | E22: =IF($A22>$B$8,"",C22*INDEX(Decrements!$E$6:$E$58,$B$7+$A22-18)) -> 0.021143308 | F22: =IF($A22>$B$8,"",IF($A22=$B$8,C22*INDEX(Decrements!$F$6:$F$58,$B$7+$A22-18),0)) -> 0 | G22: =IF($A22>$B$8,"",$B$6+$A22) -> 20.900068 | H22: =IF($A22>$B$8,"",$B$9*(1+Assumptions!$B$9)^$A22) -> 170354.13 | I22: =IF($A22>$B$8,"",INT(G22)+IF(G22-INT(G22)>0.5,1,0)) -> 21 | J22: =IF($A22>$B$8,"",MIN(15/26*H22*I22,Assumptions!$B$10)) -> 2000000 | K22: =IF($A22>$B$8,"",D22+F22+E22*IF(G22>=Assumptions!$B$11,1,0)) -> 0.022482806 | L22: =IF($A22>$B$8,"",K22*J22) -> 44965.612 | M22: =IF($A22>$B$8,"",$B$6/G22) -> 0.66507287 | N22: =IF($A22>$B$8,"",(1/(1+Assumptions!$B$8))^$A22) -> 0.62274974 | O22: =IF($A22>$B$8,"",L22*M22*N22) -> 18623.585 | P22: =IF($A22>$B$8,"",L22/G22*N22) -> 1339.8197
A23: =A22+1 -> 8 | B23: =IF($A23>$B$8,"",$B$7+$A23-1) -> 46 | C23: =IF($A23>$B$8,"",INDEX(Decrements!$G$6:$G$58,$B$7+$A23-18)/INDEX(Decrements!$G$6:$G$58,$B$7-17)) -> 0.68297407 | D23: =IF($A23>$B$8,"",C23*INDEX(Decrements!$D$6:$D$58,$B$7+$A23-18)) -> 0.0013994992 | E23: =IF($A23>$B$8,"",C23*INDEX(Decrements!$E$6:$E$58,$B$7+$A23-18)) -> 0.02046791 | F23: =IF($A23>$B$8,"",IF($A23=$B$8,C23*INDEX(Decrements!$F$6:$F$58,$B$7+$A23-18),0)) -> 0 | G23: =IF($A23>$B$8,"",$B$6+$A23) -> 21.900068 | H23: =IF($A23>$B$8,"",$B$9*(1+Assumptions!$B$9)^$A23) -> 183982.46 | I23: =IF($A23>$B$8,"",INT(G23)+IF(G23-INT(G23)>0.5,1,0)) -> 22 | J23: =IF($A23>$B$8,"",MIN(15/26*H23*I23,Assumptions!$B$10)) -> 2000000 | K23: =IF($A23>$B$8,"",D23+F23+E23*IF(G23>=Assumptions!$B$11,1,0)) -> 0.021867409 | L23: =IF($A23>$B$8,"",K23*J23) -> 43734.818 | M23: =IF($A23>$B$8,"",$B$6/G23) -> 0.63470434 | N23: =IF($A23>$B$8,"",(1/(1+Assumptions!$B$8))^$A23) -> 0.5820091 | O23: =IF($A23>$B$8,"",L23*M23*N23) -> 16155.804 | P23: =IF($A23>$B$8,"",L23/G23*N23) -> 1162.2823
A24: =A23+1 -> 9 | B24: =IF($A24>$B$8,"",$B$7+$A24-1) -> 47 | C24: =IF($A24>$B$8,"",INDEX(Decrements!$G$6:$G$58,$B$7+$A24-18)/INDEX(Decrements!$G$6:$G$58,$B$7-17)) -> 0.66110666 | D24: =IF($A24>$B$8,"",C24*INDEX(Decrements!$D$6:$D$58,$B$7+$A24-18)) -> 0.0014640155 | E24: =IF($A24>$B$8,"",C24*INDEX(Decrements!$E$6:$E$58,$B$7+$A24-18)) -> 0.019810905 | F24: =IF($A24>$B$8,"",IF($A24=$B$8,C24*INDEX(Decrements!$F$6:$F$58,$B$7+$A24-18),0)) -> 0 | G24: =IF($A24>$B$8,"",$B$6+$A24) -> 22.900068 | H24: =IF($A24>$B$8,"",$B$9*(1+Assumptions!$B$9)^$A24) -> 198701.06 | I24: =IF($A24>$B$8,"",INT(G24)+IF(G24-INT(G24)>0.5,1,0)) -> 23 | J24: =IF($A24>$B$8,"",MIN(15/26*H24*I24,Assumptions!$B$10)) -> 2000000 | K24: =IF($A24>$B$8,"",D24+F24+E24*IF(G24>=Assumptions!$B$11,1,0)) -> 0.021274921 | L24: =IF($A24>$B$8,"",K24*J24) -> 42549.841 | M24: =IF($A24>$B$8,"",$B$6/G24) -> 0.60698807 | N24: =IF($A24>$B$8,"",(1/(1+Assumptions!$B$8))^$A24) -> 0.54393374 | O24: =IF($A24>$B$8,"",L24*M24*N24) -> 14048.311 | P24: =IF($A24>$B$8,"",L24/G24*N24) -> 1010.6649
A25: =A24+1 -> 10 | B25: =IF($A25>$B$8,"",$B$7+$A25-1) -> 48 | C25: =IF($A25>$B$8,"",INDEX(Decrements!$G$6:$G$58,$B$7+$A25-18)/INDEX(Decrements!$G$6:$G$58,$B$7-17)) -> 0.63983174 | D25: =IF($A25>$B$8,"",C25*INDEX(Decrements!$D$6:$D$58,$B$7+$A25-18)) -> 0.0015332697 | E25: =IF($A25>$B$8,"",C25*INDEX(Decrements!$E$6:$E$58,$B$7+$A25-18)) -> 0.019171603 | F25: =IF($A25>$B$8,"",IF($A25=$B$8,C25*INDEX(Decrements!$F$6:$F$58,$B$7+$A25-18),0)) -> 0 | G25: =IF($A25>$B$8,"",$B$6+$A25) -> 23.900068 | H25: =IF($A25>$B$8,"",$B$9*(1+Assumptions!$B$9)^$A25) -> 214597.14 | I25: =IF($A25>$B$8,"",INT(G25)+IF(G25-INT(G25)>0.5,1,0)) -> 24 | J25: =IF($A25>$B$8,"",MIN(15/26*H25*I25,Assumptions!$B$10)) -> 2000000 | K25: =IF($A25>$B$8,"",D25+F25+E25*IF(G25>=Assumptions!$B$11,1,0)) -> 0.020704873 | L25: =IF($A25>$B$8,"",K25*J25) -> 41409.745 | M25: =IF($A25>$B$8,"",$B$6/G25) -> 0.58159116 | N25: =IF($A25>$B$8,"",(1/(1+Assumptions!$B$8))^$A25) -> 0.50834929 | O25: =IF($A25>$B$8,"",L25*M25*N25) -> 12242.851 | P25: =IF($A25>$B$8,"",L25/G25*N25) -> 880.77633
A26: =A25+1 -> 11 | B26: =IF($A26>$B$8,"",$B$7+$A26-1) -> 49 | C26: =IF($A26>$B$8,"",INDEX(Decrements!$G$6:$G$58,$B$7+$A26-18)/INDEX(Decrements!$G$6:$G$58,$B$7-17)) -> 0.61912687 | D26: =IF($A26>$B$8,"",C26*INDEX(Decrements!$D$6:$D$58,$B$7+$A26-18)) -> 0.0016074912 | E26: =IF($A26>$B$8,"",C26*INDEX(Decrements!$E$6:$E$58,$B$7+$A26-18)) -> 0.018549326 | F26: =IF($A26>$B$8,"",IF($A26=$B$8,C26*INDEX(Decrements!$F$6:$F$58,$B$7+$A26-18),0)) -> 0 | G26: =IF($A26>$B$8,"",$B$6+$A26) -> 24.900068 | H26: =IF($A26>$B$8,"",$B$9*(1+Assumptions!$B$9)^$A26) -> 231764.92 | I26: =IF($A26>$B$8,"",INT(G26)+IF(G26-INT(G26)>0.5,1,0)) -> 25 | J26: =IF($A26>$B$8,"",MIN(15/26*H26*I26,Assumptions!$B$10)) -> 2000000 | K26: =IF($A26>$B$8,"",D26+F26+E26*IF(G26>=Assumptions!$B$11,1,0)) -> 0.020156818 | L26: =IF($A26>$B$8,"",K26*J26) -> 40313.635 | M26: =IF($A26>$B$8,"",$B$6/G26) -> 0.55823415 | N26: =IF($A26>$B$8,"",(1/(1+Assumptions!$B$8))^$A26) -> 0.4750928 | O26: =IF($A26>$B$8,"",L26*M26*N26) -> 10691.701 | P26: =IF($A26>$B$8,"",L26/G26*N26) -> 769.18333
A27: =A26+1 -> 12 | B27: =IF($A27>$B$8,"",$B$7+$A27-1) -> 50 | C27: =IF($A27>$B$8,"",INDEX(Decrements!$G$6:$G$58,$B$7+$A27-18)/INDEX(Decrements!$G$6:$G$58,$B$7-17)) -> 0.59897005 | D27: =IF($A27>$B$8,"",C27*INDEX(Decrements!$D$6:$D$58,$B$7+$A27-18)) -> 0.0016954779 | E27: =IF($A27>$B$8,"",C27*INDEX(Decrements!$E$6:$E$58,$B$7+$A27-18)) -> 0.011962275 | F27: =IF($A27>$B$8,"",IF($A27=$B$8,C27*INDEX(Decrements!$F$6:$F$58,$B$7+$A27-18),0)) -> 0 | G27: =IF($A27>$B$8,"",$B$6+$A27) -> 25.900068 | H27: =IF($A27>$B$8,"",$B$9*(1+Assumptions!$B$9)^$A27) -> 250306.11 | I27: =IF($A27>$B$8,"",INT(G27)+IF(G27-INT(G27)>0.5,1,0)) -> 26 | J27: =IF($A27>$B$8,"",MIN(15/26*H27*I27,Assumptions!$B$10)) -> 2000000 | K27: =IF($A27>$B$8,"",D27+F27+E27*IF(G27>=Assumptions!$B$11,1,0)) -> 0.013657753 | L27: =IF($A27>$B$8,"",K27*J27) -> 27315.506 | M27: =IF($A27>$B$8,"",$B$6/G27) -> 0.53668076 | N27: =IF($A27>$B$8,"",(1/(1+Assumptions!$B$8))^$A27) -> 0.44401196 | O27: =IF($A27>$B$8,"",L27*M27*N27) -> 6509.0849 | P27: =IF($A27>$B$8,"",L27/G27*N27) -> 468.27719
A28: =A27+1 -> 13 | B28: =IF($A28>$B$8,"",$B$7+$A28-1) -> 51 | C28: =IF($A28>$B$8,"",INDEX(Decrements!$G$6:$G$58,$B$7+$A28-18)/INDEX(Decrements!$G$6:$G$58,$B$7-17)) -> 0.5853123 | D28: =IF($A28>$B$8,"",C28*INDEX(Decrements!$D$6:$D$58,$B$7+$A28-18)) -> 0.0017991325 | E28: =IF($A28>$B$8,"",C28*INDEX(Decrements!$E$6:$E$58,$B$7+$A28-18)) -> 0.011688073 | F28: =IF($A28>$B$8,"",IF($A28=$B$8,C28*INDEX(Decrements!$F$6:$F$58,$B$7+$A28-18),0)) -> 0 | G28: =IF($A28>$B$8,"",$B$6+$A28) -> 26.900068 | H28: =IF($A28>$B$8,"",$B$9*(1+Assumptions!$B$9)^$A28) -> 270330.6 | I28: =IF($A28>$B$8,"",INT(G28)+IF(G28-INT(G28)>0.5,1,0)) -> 27 | J28: =IF($A28>$B$8,"",MIN(15/26*H28*I28,Assumptions!$B$10)) -> 2000000 | K28: =IF($A28>$B$8,"",D28+F28+E28*IF(G28>=Assumptions!$B$11,1,0)) -> 0.013487205 | L28: =IF($A28>$B$8,"",K28*J28) -> 26974.411 | M28: =IF($A28>$B$8,"",$B$6/G28) -> 0.51672985 | N28: =IF($A28>$B$8,"",(1/(1+Assumptions!$B$8))^$A28) -> 0.41496445 | O28: =IF($A28>$B$8,"",L28*M28*N28) -> 5783.975 | P28: =IF($A28>$B$8,"",L28/G28*N28) -> 416.11126
... A60: =A59+1 -> 45 | B60: =IF($A60>$B$8,"",$B$7+$A60-1) | C60: =IF($A60>$B$8,"",INDEX(Decrements!$G$6:$G$58,$B$7+$A60-18)/INDEX(Decrements!$G$6:$G$58,$B$7-17)) | D60: =IF($A60>$B$8,"",C60*INDEX(Decrements!$D$6:$D$58,$B$7+$A60-18)) | E60: =IF($A60>$B$8,"",C60*INDEX(Decrements!$E$6:$E$58,$B$7+$A60-18)) | F60: =IF($A60>$B$8,"",IF($A60=$B$8,C60*INDEX(Decrements!$F$6:$F$58,$B$7+$A60-18),0)) | G60: =IF($A60>$B$8,"",$B$6+$A60) | H60: =IF($A60>$B$8,"",$B$9*(1+Assumptions!$B$9)^$A60) | I60: =IF($A60>$B$8,"",INT(G60)+IF(G60-INT(G60)>0.5,1,0)) | J60: =IF($A60>$B$8,"",MIN(15/26*H60*I60,Assumptions!$B$10)) | K60: =IF($A60>$B$8,"",D60+F60+E60*IF(G60>=Assumptions!$B$11,1,0)) | L60: =IF($A60>$B$8,"",K60*J60) | M60: =IF($A60>$B$8,"",$B$6/G60) | N60: =IF($A60>$B$8,"",(1/(1+Assumptions!$B$8))^$A60) | O60: =IF($A60>$B$8,"",L60*M60*N60) | P60: =IF($A60>$B$8,"",L60/G60*N60)

Sheet Hand_Check
A1: Hand check: the worked example from the theory lesson
A2: One employee who retires at 60 with certainty. No exits before 60. Input values are from the lesson.
A4: Item | B4: Value
A5: Age now | B5: 40
A6: Service now (years) | B6: 10
A7: Monthly wages now (Rs) | B7: 60000
A8: Retirement age | B8: 60
A9: Wage growth | B9: 0.06
A10: Discount rate | B10: 0.07
A11: Ceiling (Rs) | B11: 2000000
A12: Years to retirement | B12: =B8-B5 -> 20
A13: Wages at retirement (Rs) | B13: =B7*(1+B9)^B12 -> 192428.13
A14: Service at retirement (years) | B14: =B6+B12 -> 30
A15: Benefit before ceiling (Rs) | B15: =15/26*B13*B14 -> 3330486.8
A16: Benefit after ceiling (Rs) | B16: =MIN(B15,B11) -> 2000000
A17: Discount factor | B17: =(1+B10)^-B12 -> 0.258419
A18: DBO (Rs) | B18: =B16*B6/B14*B17 -> 172279.34
A19: Current service cost (Rs) | B19: =B16/B14*B17 -> 17227.934
A21: Expected from the lesson: DBO (Rs) | B21: 172279
A22: Expected from the lesson: service cost (Rs) | B22: 17228
A23: Result | B23: =IF(AND(ABS(B18-B21)<5,ABS(B19-B22)<2),"PASS","CHECK") -> PASS
A25: Source of the expected values: hand calculation in the theory lesson (Stage 0).

Sheet Check_vs_Python
A1: Cross-check: Excel against the Python notebook (Stage 3)
A2: Python values are pasted outputs from the Stage 3 notebook run with the same inputs and assumptions (blue = hardcoded).
A4: Measure | B4: Excel | C4: Python (pasted) | D4: Difference | E4: Tolerance | F4: Status
A5: DBO (Rs) | B5: =Summary!B7 -> 46785528 | C5: 46785528 | D5: =B5-C5 -> 0 | E5: 1 | F5: =IF(ABS(D5)<=E5,"PASS","CHECK") -> PASS
A6: Current service cost (Rs) | B6: =Summary!B8 -> 3723248.4 | C6: 3723248.4 | D6: =B6-C6 -> 0 | E6: 1 | F6: =IF(ABS(D6)<=E6,"PASS","CHECK") -> PASS
A7: Expected payments, year 1 (Rs) | B7: =Summary!B10 -> 3990406 | C7: 3990406 | D7: =B7-C7 -> -4.1909516e-09 | E7: 1 | F7: =IF(ABS(D7)<=E7,"PASS","CHECK") -> PASS
A8: Weighted average term (years) | B8: =Summary!B11 -> 8.675623 | C8: 8.675623 | D8: =B8-C8 -> 0 | E8: 0.001 | F8: =IF(ABS(D8)<=E8,"PASS","CHECK") -> PASS
A9: Benefit if eligible left today (Rs) | B9: =Summary!B12 -> 78425827 | C9: 78425827 | D9: =B9-C9 -> 0 | E9: 1 | F9: =IF(ABS(D9)<=E9,"PASS","CHECK") -> PASS
A10: Top 10 share of DBO | B10: =Summary!B14 -> 0.22813265 | C10: 0.22813265 | D10: =B10-C10 -> 0 | E10: 0.0001 | F10: =IF(ABS(D10)<=E10,"PASS","CHECK") -> PASS
A11: Largest per-employee difference in DBO (Rs) | B11: =MAX(MAX(Census!$O$6:$O$155),-MIN(Census!$O$6:$O$155)) -> 4.9779192e-07 | E11: 0.01 | F11: =IF(B11<=E11,"PASS","CHECK") -> PASS
A12: Hand-check example (Hand_Check sheet) | F12: =Hand_Check!B23 -> PASS
A14: Overall | F14: =IF(COUNTIF(F5:F12,"PASS")=8,"ALL PASS","CHECK") -> ALL PASS
